{
  "generated_at": "2026-07-10 08:26",
  "asof": "2026-07-10",
  "source": "sepa-trend-candidates.json",
  "params": {
    "lookback_days": 250,
    "min_total_days": 40,
    "min_cup_depth": 12.0,
    "max_cup_depth": 50.0,
    "min_cup_days": 17,
    "min_shelf_pullback": 3.0,
    "min_shelf_days": 2,
    "max_shelf_days": 25,
    "max_shelf_depth": 12.0,
    "min_shelf_position": 25.0,
    "max_shelf_position": 90.0,
    "breakout_vol_mult": 1.4,
    "near_pivot_pct": 5.0
  },
  "pattern_count": 4,
  "entry_ready_count": 3,
  "status_distribution": {
    "breakout": 3,
    "actionable": 7,
    "forming": 22,
    "failed": 19
  },
  "candidates": [
    {
      "code": "339950",
      "name": "아이비김영",
      "market": "KOSDAQ",
      "current_price": 2690.0,
      "rs": 87,
      "pattern_detected": true,
      "entry_ready": true,
      "cup_depth_pct": 21.49,
      "cup_base_days": 49,
      "shelf_position_pct": 70.86,
      "shelf_depth_pct": 4.15,
      "shelf_length_days": 2,
      "pivot_price": 2769.99,
      "pct_to_pivot": 2.89,
      "volume_dryup_ratio": 0.787,
      "rally_vol_ratio": 0.734,
      "tightness_pct": 4.38,
      "status": "actionable",
      "reason": null,
      "left_rim_date": "2026-04-27",
      "cup_low_date": "2026-06-29",
      "shelf_high_date": "2026-07-07"
    },
    {
      "code": "003650",
      "name": "미창석유",
      "market": "KOSPI",
      "current_price": 136800.0,
      "rs": 84,
      "pattern_detected": true,
      "entry_ready": true,
      "cup_depth_pct": 35.43,
      "cup_base_days": 88,
      "shelf_position_pct": 55.7,
      "shelf_depth_pct": 6.75,
      "shelf_length_days": 5,
      "pivot_price": 142513.69,
      "pct_to_pivot": 4.01,
      "volume_dryup_ratio": 0.775,
      "rally_vol_ratio": 0.261,
      "tightness_pct": 4.62,
      "status": "actionable",
      "reason": null,
      "left_rim_date": "2026-03-03",
      "cup_low_date": "2026-03-31",
      "shelf_high_date": "2026-07-02"
    },
    {
      "code": "007070",
      "name": "GS리테일",
      "market": "KOSPI",
      "current_price": 25000.0,
      "rs": 90,
      "pattern_detected": true,
      "entry_ready": true,
      "cup_depth_pct": 29.72,
      "cup_base_days": 37,
      "shelf_position_pct": 58.44,
      "shelf_depth_pct": 7.05,
      "shelf_length_days": 2,
      "pivot_price": 26250.82,
      "pct_to_pivot": 4.76,
      "volume_dryup_ratio": 0.973,
      "rally_vol_ratio": 0.782,
      "tightness_pct": 6.03,
      "status": "actionable",
      "reason": null,
      "left_rim_date": "2026-05-15",
      "cup_low_date": "2026-06-26",
      "shelf_high_date": "2026-07-07"
    },
    {
      "code": "071200",
      "name": "인피니트헬스케어",
      "market": "KOSDAQ",
      "current_price": 7910.0,
      "rs": 82,
      "pattern_detected": false,
      "entry_ready": false,
      "cup_depth_pct": 35.41,
      "cup_base_days": 35,
      "shelf_position_pct": 31.66,
      "shelf_depth_pct": 4.74,
      "shelf_length_days": 2,
      "pivot_price": 6960.19,
      "pct_to_pivot": -13.65,
      "volume_dryup_ratio": 3.79,
      "rally_vol_ratio": 0.424,
      "tightness_pct": 7.14,
      "status": "breakout",
      "reason": "volume_not_drying",
      "left_rim_date": "2026-05-19",
      "cup_low_date": "2026-06-26",
      "shelf_high_date": "2026-07-07"
    },
    {
      "code": "222040",
      "name": "코스맥스엔비티",
      "market": "KOSDAQ",
      "current_price": 7930.0,
      "rs": 92,
      "pattern_detected": false,
      "entry_ready": false,
      "cup_depth_pct": 41.85,
      "cup_base_days": 32,
      "shelf_position_pct": 60.53,
      "shelf_depth_pct": 8.98,
      "shelf_length_days": 1,
      "pivot_price": 7680.0,
      "pct_to_pivot": -3.26,
      "volume_dryup_ratio": 1.74,
      "rally_vol_ratio": 1.005,
      "tightness_pct": 9.4,
      "status": "breakout",
      "reason": "shelf_too_short",
      "left_rim_date": "2026-05-22",
      "cup_low_date": "2026-06-26",
      "shelf_high_date": "2026-07-08"
    },
    {
      "code": "001540",
      "name": "안국약품",
      "market": "KOSDAQ",
      "current_price": 10940.0,
      "rs": 88,
      "pattern_detected": false,
      "entry_ready": false,
      "cup_depth_pct": 27.25,
      "cup_base_days": 30,
      "shelf_position_pct": 43.77,
      "shelf_depth_pct": 5.75,
      "shelf_length_days": 1,
      "pivot_price": 10780.0,
      "pct_to_pivot": -1.48,
      "volume_dryup_ratio": 1.402,
      "rally_vol_ratio": 0.205,
      "tightness_pct": 4.86,
      "status": "breakout",
      "reason": "shelf_too_short",
      "left_rim_date": "2026-05-27",
      "cup_low_date": "2026-06-26",
      "shelf_high_date": "2026-07-08"
    },
    {
      "code": "012510",
      "name": "더존비즈온",
      "market": "KOSPI",
      "current_price": 120000.0,
      "rs": 93,
      "pattern_detected": false,
      "entry_ready": false,
      "cup_depth_pct": 23.72,
      "cup_base_days": 27,
      "shelf_position_pct": 4.05,
      "shelf_depth_pct": 1.08,
      "shelf_length_days": 19,
      "pivot_price": 120503.44,
      "pct_to_pivot": 0.42,
      "volume_dryup_ratio": 0.0,
      "rally_vol_ratio": 2.457,
      "tightness_pct": 0.0,
      "status": "actionable",
      "reason": "shelf_too_low_in_cup",
      "left_rim_date": "2026-06-01",
      "cup_low_date": "2026-06-11",
      "shelf_high_date": "2026-06-12"
    },
    {
      "code": "037760",
      "name": "쎄니트",
      "market": "KOSDAQ",
      "current_price": 2470.0,
      "rs": 90,
      "pattern_detected": false,
      "entry_ready": false,
      "cup_depth_pct": 15.45,
      "cup_base_days": 35,
      "shelf_position_pct": 84.86,
      "shelf_depth_pct": 8.22,
      "shelf_length_days": 1,
      "pivot_price": 2495.0,
      "pct_to_pivot": 1.0,
      "volume_dryup_ratio": 0.234,
      "rally_vol_ratio": 1.429,
      "tightness_pct": 5.91,
      "status": "actionable",
      "reason": "shelf_too_short",
      "left_rim_date": "2026-05-19",
      "cup_low_date": "2026-06-30",
      "shelf_high_date": "2026-07-08"
    },
    {
      "code": "025890",
      "name": "한국주강",
      "market": "KOSPI",
      "current_price": 2205.0,
      "rs": 82,
      "pattern_detected": false,
      "entry_ready": false,
      "cup_depth_pct": 24.27,
      "cup_base_days": 58,
      "shelf_position_pct": 92.95,
      "shelf_depth_pct": 5.87,
      "shelf_length_days": 1,
      "pivot_price": 2300.0,
      "pct_to_pivot": 4.13,
      "volume_dryup_ratio": 0.708,
      "rally_vol_ratio": 0.358,
      "tightness_pct": 2.68,
      "status": "actionable",
      "reason": "shelf_too_short",
      "left_rim_date": "2026-04-14",
      "cup_low_date": "2026-06-09",
      "shelf_high_date": "2026-07-08"
    },
    {
      "code": "900260",
      "name": "로스웰",
      "market": "KOSDAQ",
      "current_price": 1651.0,
      "rs": 97,
      "pattern_detected": false,
      "entry_ready": false,
      "cup_depth_pct": 33.94,
      "cup_base_days": 6,
      "shelf_position_pct": 42.17,
      "shelf_depth_pct": 6.09,
      "shelf_length_days": 5,
      "pivot_price": 1724.06,
      "pct_to_pivot": 4.24,
      "volume_dryup_ratio": 0.039,
      "rally_vol_ratio": 0.521,
      "tightness_pct": 8.39,
      "status": "actionable",
      "reason": "cup_too_short",
      "left_rim_date": "2026-07-01",
      "cup_low_date": "2026-07-01",
      "shelf_high_date": "2026-07-02"
    },
    {
      "code": "057050",
      "name": "현대홈쇼핑",
      "market": "KOSPI",
      "current_price": 87300.0,
      "rs": 91,
      "pattern_detected": true,
      "entry_ready": false,
      "cup_depth_pct": 25.0,
      "cup_base_days": 91,
      "shelf_position_pct": 56.49,
      "shelf_depth_pct": 9.79,
      "shelf_length_days": 16,
      "pivot_price": 85793.59,
      "pct_to_pivot": -1.76,
      "volume_dryup_ratio": 0.0,
      "rally_vol_ratio": 0.69,
      "tightness_pct": 0.0,
      "status": "forming",
      "reason": null,
      "left_rim_date": "2026-02-25",
      "cup_low_date": "2026-06-09",
      "shelf_high_date": "2026-06-17"
    },
    {
      "code": "033560",
      "name": "블루콤",
      "market": "KOSDAQ",
      "current_price": 3845.0,
      "rs": 82,
      "pattern_detected": false,
      "entry_ready": false,
      "cup_depth_pct": 14.14,
      "cup_base_days": 6,
      "shelf_position_pct": 49.63,
      "shelf_depth_pct": 6.25,
      "shelf_length_days": 1,
      "pivot_price": 3840.0,
      "pct_to_pivot": -0.13,
      "volume_dryup_ratio": 1.023,
      "rally_vol_ratio": 0.638,
      "tightness_pct": 5.64,
      "status": "forming",
      "reason": "cup_too_short",
      "left_rim_date": "2026-07-01",
      "cup_low_date": "2026-07-03",
      "shelf_high_date": "2026-07-08"
    },
    {
      "code": "010950",
      "name": "S-Oil",
      "market": "KOSPI",
      "current_price": 133500.0,
      "rs": 96,
      "pattern_detected": false,
      "entry_ready": false,
      "cup_depth_pct": 48.96,
      "cup_base_days": 87,
      "shelf_position_pct": 51.1,
      "shelf_depth_pct": 7.8,
      "shelf_length_days": 1,
      "pivot_price": 134700.0,
      "pct_to_pivot": 0.89,
      "volume_dryup_ratio": 1.225,
      "rally_vol_ratio": 0.669,
      "tightness_pct": 6.99,
      "status": "forming",
      "reason": "shelf_too_short",
      "left_rim_date": "2026-03-04",
      "cup_low_date": "2026-06-26",
      "shelf_high_date": "2026-07-08"
    },
    {
      "code": "094860",
      "name": "네오리진",
      "market": "KOSDAQ",
      "current_price": 1419.0,
      "rs": 88,
      "pattern_detected": false,
      "entry_ready": false,
      "cup_depth_pct": 35.42,
      "cup_base_days": 51,
      "shelf_position_pct": 37.82,
      "shelf_depth_pct": 10.28,
      "shelf_length_days": 1,
      "pivot_price": 1449.0,
      "pct_to_pivot": 2.07,
      "volume_dryup_ratio": 1.203,
      "rally_vol_ratio": 0.542,
      "tightness_pct": 6.59,
      "status": "forming",
      "reason": "shelf_too_short",
      "left_rim_date": "2026-04-23",
      "cup_low_date": "2026-06-26",
      "shelf_high_date": "2026-07-08"
    },
    {
      "code": "204610",
      "name": "티쓰리",
      "market": "KOSDAQ",
      "current_price": 3005.0,
      "rs": 89,
      "pattern_detected": false,
      "entry_ready": false,
      "cup_depth_pct": 43.35,
      "cup_base_days": 49,
      "shelf_position_pct": 57.77,
      "shelf_depth_pct": 6.46,
      "shelf_length_days": 3,
      "pivot_price": 3100.09,
      "pct_to_pivot": 3.07,
      "volume_dryup_ratio": 1.141,
      "rally_vol_ratio": 0.985,
      "tightness_pct": 6.11,
      "status": "forming",
      "reason": "volume_not_drying",
      "left_rim_date": "2026-04-27",
      "cup_low_date": "2026-06-24",
      "shelf_high_date": "2026-07-06"
    },
    {
      "code": "105560",
      "name": "KB금융",
      "market": "KOSPI",
      "current_price": 171400.0,
      "rs": 91,
      "pattern_detected": false,
      "entry_ready": false,
      "cup_depth_pct": 20.63,
      "cup_base_days": 17,
      "shelf_position_pct": 84.95,
      "shelf_depth_pct": 4.8,
      "shelf_length_days": 3,
      "pivot_price": 176992.32,
      "pct_to_pivot": 3.16,
      "volume_dryup_ratio": 1.221,
      "rally_vol_ratio": 0.975,
      "tightness_pct": 5.15,
      "status": "forming",
      "reason": "volume_not_drying",
      "left_rim_date": "2026-06-16",
      "cup_low_date": "2026-06-26",
      "shelf_high_date": "2026-07-06"
    },
    {
      "code": "092230",
      "name": "KPX홀딩스",
      "market": "KOSPI",
      "current_price": 86500.0,
      "rs": 85,
      "pattern_detected": false,
      "entry_ready": false,
      "cup_depth_pct": 17.68,
      "cup_base_days": 45,
      "shelf_position_pct": 82.87,
      "shelf_depth_pct": 6.04,
      "shelf_length_days": 2,
      "pivot_price": 89400.0,
      "pct_to_pivot": 3.24,
      "volume_dryup_ratio": 1.66,
      "rally_vol_ratio": 1.465,
      "tightness_pct": 3.55,
      "status": "forming",
      "reason": "volume_not_drying",
      "left_rim_date": "2026-05-04",
      "cup_low_date": "2026-06-26",
      "shelf_high_date": "2026-07-07"
    },
    {
      "code": "010955",
      "name": "S-Oil우",
      "market": "KOSPI",
      "current_price": 65000.0,
      "rs": 93,
      "pattern_detected": false,
      "entry_ready": false,
      "cup_depth_pct": 34.54,
      "cup_base_days": 87,
      "shelf_position_pct": 69.69,
      "shelf_depth_pct": 8.32,
      "shelf_length_days": 1,
      "pivot_price": 67300.0,
      "pct_to_pivot": 3.42,
      "volume_dryup_ratio": 1.292,
      "rally_vol_ratio": 0.726,
      "tightness_pct": 5.6,
      "status": "forming",
      "reason": "shelf_too_short",
      "left_rim_date": "2026-03-04",
      "cup_low_date": "2026-06-26",
      "shelf_high_date": "2026-07-08"
    },
    {
      "code": "086790",
      "name": "하나금융지주",
      "market": "KOSPI",
      "current_price": 122600.0,
      "rs": 89,
      "pattern_detected": false,
      "entry_ready": false,
      "cup_depth_pct": 20.89,
      "cup_base_days": 17,
      "shelf_position_pct": 73.21,
      "shelf_depth_pct": 7.17,
      "shelf_length_days": 1,
      "pivot_price": 128400.0,
      "pct_to_pivot": 4.52,
      "volume_dryup_ratio": 1.06,
      "rally_vol_ratio": 1.113,
      "tightness_pct": 5.09,
      "status": "forming",
      "reason": "shelf_too_short",
      "left_rim_date": "2026-06-16",
      "cup_low_date": "2026-06-26",
      "shelf_high_date": "2026-07-08"
    },
    {
      "code": "041830",
      "name": "인바디",
      "market": "KOSDAQ",
      "current_price": 55500.0,
      "rs": 96,
      "pattern_detected": false,
      "entry_ready": false,
      "cup_depth_pct": 20.4,
      "cup_base_days": 6,
      "shelf_position_pct": 60.34,
      "shelf_depth_pct": 9.32,
      "shelf_length_days": 0,
      "pivot_price": 59000.0,
      "pct_to_pivot": 5.93,
      "volume_dryup_ratio": 1.066,
      "rally_vol_ratio": 0.781,
      "tightness_pct": 13.09,
      "status": "forming",
      "reason": "cup_too_short",
      "left_rim_date": "2026-07-01",
      "cup_low_date": "2026-07-08",
      "shelf_high_date": "2026-07-09"
    },
    {
      "code": "036800",
      "name": "나이스정보통신",
      "market": "KOSDAQ",
      "current_price": 30100.0,
      "rs": 88,
      "pattern_detected": false,
      "entry_ready": false,
      "cup_depth_pct": 30.41,
      "cup_base_days": 53,
      "shelf_position_pct": 60.59,
      "shelf_depth_pct": 9.06,
      "shelf_length_days": 3,
      "pivot_price": 32001.11,
      "pct_to_pivot": 5.94,
      "volume_dryup_ratio": 1.536,
      "rally_vol_ratio": 0.342,
      "tightness_pct": 5.45,
      "status": "forming",
      "reason": "volume_not_drying",
      "left_rim_date": "2026-04-21",
      "cup_low_date": "2026-06-02",
      "shelf_high_date": "2026-07-06"
    },
    {
      "code": "069730",
      "name": "DSR제강",
      "market": "KOSPI",
      "current_price": 5440.0,
      "rs": 89,
      "pattern_detected": false,
      "entry_ready": false,
      "cup_depth_pct": 19.05,
      "cup_base_days": 44,
      "shelf_position_pct": 92.79,
      "shelf_depth_pct": 7.93,
      "shelf_length_days": 3,
      "pivot_price": 5799.73,
      "pct_to_pivot": 6.2,
      "volume_dryup_ratio": 0.444,
      "rally_vol_ratio": 1.66,
      "tightness_pct": 5.59,
      "status": "forming",
      "reason": "shelf_too_high_in_cup",
      "left_rim_date": "2026-05-06",
      "cup_low_date": "2026-06-24",
      "shelf_high_date": "2026-07-06"
    },
    {
      "code": "094840",
      "name": "슈프리마에이치큐",
      "market": "KOSDAQ",
      "current_price": 11770.0,
      "rs": 91,
      "pattern_detected": false,
      "entry_ready": false,
      "cup_depth_pct": 32.38,
      "cup_base_days": 43,
      "shelf_position_pct": 99.27,
      "shelf_depth_pct": 10.34,
      "shelf_length_days": 5,
      "pivot_price": 12759.97,
      "pct_to_pivot": 7.76,
      "volume_dryup_ratio": 0.757,
      "rally_vol_ratio": 1.1,
      "tightness_pct": 5.43,
      "status": "forming",
      "reason": "shelf_too_high_in_cup",
      "left_rim_date": "2026-05-07",
      "cup_low_date": "2026-06-08",
      "shelf_high_date": "2026-07-02"
    },
    {
      "code": "078930",
      "name": "GS",
      "market": "KOSPI",
      "current_price": 75600.0,
      "rs": 92,
      "pattern_detected": false,
      "entry_ready": false,
      "cup_depth_pct": 29.86,
      "cup_base_days": 37,
      "shelf_position_pct": 83.07,
      "shelf_depth_pct": 8.87,
      "shelf_length_days": 2,
      "pivot_price": 82297.77,
      "pct_to_pivot": 8.14,
      "volume_dryup_ratio": 1.184,
      "rally_vol_ratio": 1.26,
      "tightness_pct": 7.73,
      "status": "forming",
      "reason": "volume_not_drying",
      "left_rim_date": "2026-05-15",
      "cup_low_date": "2026-06-26",
      "shelf_high_date": "2026-07-07"
    },
    {
      "code": "004170",
      "name": "신세계",
      "market": "KOSPI",
      "current_price": 606000.0,
      "rs": 98,
      "pattern_detected": false,
      "entry_ready": false,
      "cup_depth_pct": null,
      "cup_base_days": null,
      "shelf_position_pct": null,
      "shelf_depth_pct": null,
      "shelf_length_days": null,
      "pivot_price": null,
      "pct_to_pivot": null,
      "volume_dryup_ratio": null,
      "rally_vol_ratio": null,
      "tightness_pct": null,
      "status": "forming",
      "reason": "no_overhead_cup",
      "left_rim_date": null,
      "cup_low_date": null,
      "shelf_high_date": null
    },
    {
      "code": "019210",
      "name": "와이지-원",
      "market": "KOSDAQ",
      "current_price": 22200.0,
      "rs": 98,
      "pattern_detected": false,
      "entry_ready": false,
      "cup_depth_pct": null,
      "cup_base_days": null,
      "shelf_position_pct": null,
      "shelf_depth_pct": null,
      "shelf_length_days": null,
      "pivot_price": null,
      "pct_to_pivot": null,
      "volume_dryup_ratio": null,
      "rally_vol_ratio": null,
      "tightness_pct": null,
      "status": "forming",
      "reason": "no_overhead_cup",
      "left_rim_date": null,
      "cup_low_date": null,
      "shelf_high_date": null
    },
    {
      "code": "002995",
      "name": "금호건설우",
      "market": "KOSPI",
      "current_price": 45200.0,
      "rs": 98,
      "pattern_detected": false,
      "entry_ready": false,
      "cup_depth_pct": null,
      "cup_base_days": null,
      "shelf_position_pct": null,
      "shelf_depth_pct": null,
      "shelf_length_days": null,
      "pivot_price": null,
      "pct_to_pivot": null,
      "volume_dryup_ratio": null,
      "rally_vol_ratio": null,
      "tightness_pct": null,
      "status": "forming",
      "reason": "no_overhead_cup",
      "left_rim_date": null,
      "cup_low_date": null,
      "shelf_high_date": null
    },
    {
      "code": "069960",
      "name": "현대백화점",
      "market": "KOSPI",
      "current_price": 167600.0,
      "rs": 96,
      "pattern_detected": false,
      "entry_ready": false,
      "cup_depth_pct": null,
      "cup_base_days": null,
      "shelf_position_pct": null,
      "shelf_depth_pct": null,
      "shelf_length_days": null,
      "pivot_price": null,
      "pct_to_pivot": null,
      "volume_dryup_ratio": null,
      "rally_vol_ratio": null,
      "tightness_pct": null,
      "status": "forming",
      "reason": "no_overhead_cup",
      "left_rim_date": null,
      "cup_low_date": null,
      "shelf_high_date": null
    },
    {
      "code": "055550",
      "name": "신한지주",
      "market": "KOSPI",
      "current_price": 105000.0,
      "rs": 93,
      "pattern_detected": false,
      "entry_ready": false,
      "cup_depth_pct": null,
      "cup_base_days": null,
      "shelf_position_pct": null,
      "shelf_depth_pct": null,
      "shelf_length_days": null,
      "pivot_price": null,
      "pct_to_pivot": null,
      "volume_dryup_ratio": null,
      "rally_vol_ratio": null,
      "tightness_pct": null,
      "status": "forming",
      "reason": "no_overhead_cup",
      "left_rim_date": null,
      "cup_low_date": null,
      "shelf_high_date": null
    },
    {
      "code": "189330",
      "name": "씨이랩",
      "market": "KOSDAQ",
      "current_price": 13130.0,
      "rs": 91,
      "pattern_detected": false,
      "entry_ready": false,
      "cup_depth_pct": null,
      "cup_base_days": null,
      "shelf_position_pct": null,
      "shelf_depth_pct": null,
      "shelf_length_days": null,
      "pivot_price": null,
      "pct_to_pivot": null,
      "volume_dryup_ratio": null,
      "rally_vol_ratio": null,
      "tightness_pct": null,
      "status": "forming",
      "reason": "no_overhead_cup",
      "left_rim_date": null,
      "cup_low_date": null,
      "shelf_high_date": null
    },
    {
      "code": "005430",
      "name": "한국공항",
      "market": "KOSPI",
      "current_price": 79400.0,
      "rs": 90,
      "pattern_detected": false,
      "entry_ready": false,
      "cup_depth_pct": null,
      "cup_base_days": null,
      "shelf_position_pct": null,
      "shelf_depth_pct": null,
      "shelf_length_days": null,
      "pivot_price": null,
      "pct_to_pivot": null,
      "volume_dryup_ratio": null,
      "rally_vol_ratio": null,
      "tightness_pct": null,
      "status": "forming",
      "reason": "no_overhead_cup",
      "left_rim_date": null,
      "cup_low_date": null,
      "shelf_high_date": null
    },
    {
      "code": "161890",
      "name": "한국콜마",
      "market": "KOSPI",
      "current_price": 102800.0,
      "rs": 80,
      "pattern_detected": false,
      "entry_ready": false,
      "cup_depth_pct": null,
      "cup_base_days": null,
      "shelf_position_pct": null,
      "shelf_depth_pct": null,
      "shelf_length_days": null,
      "pivot_price": null,
      "pct_to_pivot": null,
      "volume_dryup_ratio": null,
      "rally_vol_ratio": null,
      "tightness_pct": null,
      "status": "forming",
      "reason": "no_overhead_cup",
      "left_rim_date": null,
      "cup_low_date": null,
      "shelf_high_date": null
    },
    {
      "code": "002990",
      "name": "금호건설",
      "market": "KOSPI",
      "current_price": 17310.0,
      "rs": 99,
      "pattern_detected": false,
      "entry_ready": false,
      "cup_depth_pct": 54.23,
      "cup_base_days": 5,
      "shelf_position_pct": 69.66,
      "shelf_depth_pct": 29.07,
      "shelf_length_days": 2,
      "pivot_price": 15790.0,
      "pct_to_pivot": -9.63,
      "volume_dryup_ratio": 0.698,
      "rally_vol_ratio": 1.149,
      "tightness_pct": 28.25,
      "status": "failed",
      "reason": "cup_too_deep",
      "left_rim_date": "2026-07-02",
      "cup_low_date": "2026-07-06",
      "shelf_high_date": "2026-07-07"
    },
    {
      "code": "040350",
      "name": "크레오에스지",
      "market": "KOSDAQ",
      "current_price": 9400.0,
      "rs": 85,
      "pattern_detected": false,
      "entry_ready": false,
      "cup_depth_pct": 50.39,
      "cup_base_days": 19,
      "shelf_position_pct": 34.89,
      "shelf_depth_pct": 12.33,
      "shelf_length_days": 2,
      "pivot_price": 8600.13,
      "pct_to_pivot": -9.3,
      "volume_dryup_ratio": 0.613,
      "rally_vol_ratio": 0.447,
      "tightness_pct": 13.3,
      "status": "failed",
      "reason": "cup_too_deep",
      "left_rim_date": "2026-06-12",
      "cup_low_date": "2026-06-30",
      "shelf_high_date": "2026-07-07"
    },
    {
      "code": "290720",
      "name": "푸드나무",
      "market": "KOSDAQ",
      "current_price": 3135.0,
      "rs": 88,
      "pattern_detected": false,
      "entry_ready": false,
      "cup_depth_pct": 50.24,
      "cup_base_days": 54,
      "shelf_position_pct": 61.03,
      "shelf_depth_pct": 22.19,
      "shelf_length_days": 4,
      "pivot_price": 3199.96,
      "pct_to_pivot": 2.03,
      "volume_dryup_ratio": 1.108,
      "rally_vol_ratio": 1.252,
      "tightness_pct": 14.2,
      "status": "failed",
      "reason": "cup_too_deep",
      "left_rim_date": "2026-04-20",
      "cup_low_date": "2026-06-29",
      "shelf_high_date": "2026-07-03"
    },
    {
      "code": "017890",
      "name": "한국알콜",
      "market": "KOSDAQ",
      "current_price": 12970.0,
      "rs": 86,
      "pattern_detected": false,
      "entry_ready": false,
      "cup_depth_pct": 26.35,
      "cup_base_days": 46,
      "shelf_position_pct": 78.62,
      "shelf_depth_pct": 12.0,
      "shelf_length_days": 3,
      "pivot_price": 13750.4,
      "pct_to_pivot": 5.68,
      "volume_dryup_ratio": 1.142,
      "rally_vol_ratio": 0.914,
      "tightness_pct": 5.97,
      "status": "failed",
      "reason": "shelf_too_loose",
      "left_rim_date": "2026-04-30",
      "cup_low_date": "2026-06-08",
      "shelf_high_date": "2026-07-06"
    },
    {
      "code": "049430",
      "name": "코메론",
      "market": "KOSDAQ",
      "current_price": 19510.0,
      "rs": 94,
      "pattern_detected": false,
      "entry_ready": false,
      "cup_depth_pct": 27.29,
      "cup_base_days": 67,
      "shelf_position_pct": 55.02,
      "shelf_depth_pct": 13.3,
      "shelf_length_days": 18,
      "pivot_price": 20747.71,
      "pct_to_pivot": 5.97,
      "volume_dryup_ratio": 1.426,
      "rally_vol_ratio": 0.563,
      "tightness_pct": 3.12,
      "status": "failed",
      "reason": "shelf_too_loose",
      "left_rim_date": "2026-04-01",
      "cup_low_date": "2026-06-05",
      "shelf_high_date": "2026-06-15"
    },
    {
      "code": "066980",
      "name": "한성크린텍",
      "market": "KOSDAQ",
      "current_price": 2110.0,
      "rs": 89,
      "pattern_detected": false,
      "entry_ready": false,
      "cup_depth_pct": 33.56,
      "cup_base_days": 5,
      "shelf_position_pct": 45.7,
      "shelf_depth_pct": 17.02,
      "shelf_length_days": 0,
      "pivot_price": 2245.0,
      "pct_to_pivot": 6.01,
      "volume_dryup_ratio": 0.807,
      "rally_vol_ratio": 1.017,
      "tightness_pct": 16.71,
      "status": "failed",
      "reason": "cup_too_short",
      "left_rim_date": "2026-07-02",
      "cup_low_date": "2026-07-08",
      "shelf_high_date": "2026-07-09"
    },
    {
      "code": "420770",
      "name": "기가비스",
      "market": "KOSDAQ",
      "current_price": 151500.0,
      "rs": 99,
      "pattern_detected": false,
      "entry_ready": false,
      "cup_depth_pct": 37.08,
      "cup_base_days": 6,
      "shelf_position_pct": 41.89,
      "shelf_depth_pct": 13.37,
      "shelf_length_days": 0,
      "pivot_price": 161600.0,
      "pct_to_pivot": 6.25,
      "volume_dryup_ratio": 0.873,
      "rally_vol_ratio": 1.244,
      "tightness_pct": 13.43,
      "status": "failed",
      "reason": "cup_too_short",
      "left_rim_date": "2026-07-01",
      "cup_low_date": "2026-07-08",
      "shelf_high_date": "2026-07-09"
    },
    {
      "code": "161390",
      "name": "한국타이어앤테크놀로지",
      "market": "KOSPI",
      "current_price": 70700.0,
      "rs": 93,
      "pattern_detected": false,
      "entry_ready": false,
      "cup_depth_pct": 33.8,
      "cup_base_days": 93,
      "shelf_position_pct": 90.92,
      "shelf_depth_pct": 23.55,
      "shelf_length_days": 18,
      "pivot_price": 75994.44,
      "pct_to_pivot": 6.97,
      "volume_dryup_ratio": 0.967,
      "rally_vol_ratio": 1.043,
      "tightness_pct": 6.63,
      "status": "failed",
      "reason": "shelf_too_loose",
      "left_rim_date": "2026-02-23",
      "cup_low_date": "2026-04-03",
      "shelf_high_date": "2026-06-15"
    },
    {
      "code": "219130",
      "name": "타이거일렉",
      "market": "KOSDAQ",
      "current_price": 67600.0,
      "rs": 99,
      "pattern_detected": false,
      "entry_ready": false,
      "cup_depth_pct": 31.09,
      "cup_base_days": 18,
      "shelf_position_pct": 68.25,
      "shelf_depth_pct": 19.76,
      "shelf_length_days": 6,
      "pivot_price": 73902.09,
      "pct_to_pivot": 8.53,
      "volume_dryup_ratio": 0.619,
      "rally_vol_ratio": 1.017,
      "tightness_pct": 11.61,
      "status": "failed",
      "reason": "shelf_too_loose",
      "left_rim_date": "2026-06-15",
      "cup_low_date": "2026-06-26",
      "shelf_high_date": "2026-07-01"
    },
    {
      "code": "137080",
      "name": "나래나노텍",
      "market": "KOSDAQ",
      "current_price": 5610.0,
      "rs": 93,
      "pattern_detected": false,
      "entry_ready": false,
      "cup_depth_pct": 35.9,
      "cup_base_days": 49,
      "shelf_position_pct": 95.45,
      "shelf_depth_pct": 14.49,
      "shelf_length_days": 2,
      "pivot_price": 6139.82,
      "pct_to_pivot": 8.63,
      "volume_dryup_ratio": 1.386,
      "rally_vol_ratio": 0.909,
      "tightness_pct": 7.51,
      "status": "failed",
      "reason": "shelf_too_loose",
      "left_rim_date": "2026-04-27",
      "cup_low_date": "2026-06-08",
      "shelf_high_date": "2026-07-07"
    },
    {
      "code": "079940",
      "name": "가비아",
      "market": "KOSDAQ",
      "current_price": 31150.0,
      "rs": 82,
      "pattern_detected": false,
      "entry_ready": false,
      "cup_depth_pct": 32.24,
      "cup_base_days": 106,
      "shelf_position_pct": 83.12,
      "shelf_depth_pct": 17.99,
      "shelf_length_days": 56,
      "pivot_price": 34754.49,
      "pct_to_pivot": 10.37,
      "volume_dryup_ratio": 0.16,
      "rally_vol_ratio": 2.728,
      "tightness_pct": 4.74,
      "status": "failed",
      "reason": "shelf_too_long",
      "left_rim_date": "2026-01-30",
      "cup_low_date": "2026-03-31",
      "shelf_high_date": "2026-04-16"
    },
    {
      "code": "003690",
      "name": "코리안리",
      "market": "KOSPI",
      "current_price": 13370.0,
      "rs": 86,
      "pattern_detected": false,
      "entry_ready": false,
      "cup_depth_pct": 25.65,
      "cup_base_days": 93,
      "shelf_position_pct": 87.78,
      "shelf_depth_pct": 18.56,
      "shelf_length_days": 36,
      "pivot_price": 14919.16,
      "pct_to_pivot": 10.38,
      "volume_dryup_ratio": 0.453,
      "rally_vol_ratio": 1.67,
      "tightness_pct": 4.62,
      "status": "failed",
      "reason": "shelf_too_long",
      "left_rim_date": "2026-02-23",
      "cup_low_date": "2026-05-04",
      "shelf_high_date": "2026-05-18"
    },
    {
      "code": "005680",
      "name": "삼영전자",
      "market": "KOSPI",
      "current_price": 14770.0,
      "rs": 86,
      "pattern_detected": false,
      "entry_ready": false,
      "cup_depth_pct": 33.13,
      "cup_base_days": 31,
      "shelf_position_pct": 83.41,
      "shelf_depth_pct": 22.36,
      "shelf_length_days": 14,
      "pivot_price": 17001.19,
      "pct_to_pivot": 13.12,
      "volume_dryup_ratio": 0.845,
      "rally_vol_ratio": 0.497,
      "tightness_pct": 8.44,
      "status": "failed",
      "reason": "shelf_too_loose",
      "left_rim_date": "2026-05-26",
      "cup_low_date": "2026-06-10",
      "shelf_high_date": "2026-06-19"
    },
    {
      "code": "000810",
      "name": "삼성화재",
      "market": "KOSPI",
      "current_price": 622000.0,
      "rs": 89,
      "pattern_detected": false,
      "entry_ready": false,
      "cup_depth_pct": 21.26,
      "cup_base_days": 25,
      "shelf_position_pct": 87.55,
      "shelf_depth_pct": 18.98,
      "shelf_length_days": 14,
      "pivot_price": 736852.28,
      "pct_to_pivot": 15.59,
      "volume_dryup_ratio": 0.657,
      "rally_vol_ratio": 0.647,
      "tightness_pct": 6.03,
      "status": "failed",
      "reason": "shelf_too_loose",
      "left_rim_date": "2026-06-04",
      "cup_low_date": "2026-06-10",
      "shelf_high_date": "2026-06-19"
    },
    {
      "code": "037710",
      "name": "광주신세계",
      "market": "KOSPI",
      "current_price": 41600.0,
      "rs": 88,
      "pattern_detected": false,
      "entry_ready": false,
      "cup_depth_pct": 37.24,
      "cup_base_days": 8,
      "shelf_position_pct": 54.07,
      "shelf_depth_pct": 18.12,
      "shelf_length_days": 2,
      "pivot_price": 49399.46,
      "pct_to_pivot": 15.79,
      "volume_dryup_ratio": 0.635,
      "rally_vol_ratio": 0.91,
      "tightness_pct": 16.38,
      "status": "failed",
      "reason": "cup_too_short",
      "left_rim_date": "2026-06-29",
      "cup_low_date": "2026-07-06",
      "shelf_high_date": "2026-07-07"
    },
    {
      "code": "001450",
      "name": "현대해상",
      "market": "KOSPI",
      "current_price": 36050.0,
      "rs": 87,
      "pattern_detected": false,
      "entry_ready": false,
      "cup_depth_pct": 35.26,
      "cup_base_days": 93,
      "shelf_position_pct": 93.62,
      "shelf_depth_pct": 23.0,
      "shelf_length_days": 16,
      "pivot_price": 43246.23,
      "pct_to_pivot": 16.64,
      "volume_dryup_ratio": 0.692,
      "rally_vol_ratio": 0.412,
      "tightness_pct": 5.61,
      "status": "failed",
      "reason": "shelf_too_loose",
      "left_rim_date": "2026-02-23",
      "cup_low_date": "2026-03-04",
      "shelf_high_date": "2026-06-17"
    },
    {
      "code": "131290",
      "name": "티에스이",
      "market": "KOSDAQ",
      "current_price": 224000.0,
      "rs": 99,
      "pattern_detected": false,
      "entry_ready": false,
      "cup_depth_pct": 24.44,
      "cup_base_days": 19,
      "shelf_position_pct": 99.16,
      "shelf_depth_pct": 23.41,
      "shelf_length_days": 6,
      "pivot_price": 282003.61,
      "pct_to_pivot": 20.57,
      "volume_dryup_ratio": 1.017,
      "rally_vol_ratio": 1.007,
      "tightness_pct": 11.37,
      "status": "failed",
      "reason": "shelf_too_loose",
      "left_rim_date": "2026-06-12",
      "cup_low_date": "2026-06-26",
      "shelf_high_date": "2026-07-01"
    },
    {
      "code": "009420",
      "name": "한올바이오파마",
      "market": "KOSPI",
      "current_price": 55600.0,
      "rs": 96,
      "pattern_detected": false,
      "entry_ready": false,
      "cup_depth_pct": 36.02,
      "cup_base_days": 30,
      "shelf_position_pct": 88.63,
      "shelf_depth_pct": 21.43,
      "shelf_length_days": 8,
      "pivot_price": 69994.98,
      "pct_to_pivot": 20.57,
      "volume_dryup_ratio": 0.76,
      "rally_vol_ratio": 0.817,
      "tightness_pct": 10.2,
      "status": "failed",
      "reason": "shelf_too_loose",
      "left_rim_date": "2026-05-27",
      "cup_low_date": "2026-06-11",
      "shelf_high_date": "2026-06-29"
    },
    {
      "code": "091590",
      "name": "남화토건",
      "market": "KOSDAQ",
      "current_price": 8870.0,
      "rs": 95,
      "pattern_detected": false,
      "entry_ready": false,
      "cup_depth_pct": 38.39,
      "cup_base_days": 5,
      "shelf_position_pct": 81.62,
      "shelf_depth_pct": 27.36,
      "shelf_length_days": 2,
      "pivot_price": 11330.03,
      "pct_to_pivot": 21.71,
      "volume_dryup_ratio": 0.812,
      "rally_vol_ratio": 0.957,
      "tightness_pct": 25.61,
      "status": "failed",
      "reason": "cup_too_short",
      "left_rim_date": "2026-07-02",
      "cup_low_date": "2026-07-06",
      "shelf_high_date": "2026-07-07"
    }
  ]
}