[
 {
  "code": "103590",
  "name": "일진전기",
  "mkt": "KOSPI",
  "buy_date": "2025-04-07",
  "buy_close": 20050.0,
  "days_to_gain": 6,
  "reach_date": "2025-04-15",
  "run_max_pct": 43.6,
  "RS_pct": 85.2,
  "M_up": false,
  "vol_vs_50d": 1.2,
  "pct_52w_high": 55.3,
  "above_ma50_pct": -31.6,
  "days_from_trough": 0,
  "prior60_run_pct": 0.0,
  "I_fgn60": 61108,
  "I_org60": -2087186,
  "C_qkey": "202412",
  "C_eps_yoy": 141.0,
  "C_src": "DART"
 },
 {
  "code": "103590",
  "name": "일진전기",
  "mkt": "KOSPI",
  "buy_date": "2025-04-22",
  "buy_close": 22900.0,
  "days_to_gain": 9,
  "reach_date": "2025-05-08",
  "run_max_pct": 34.9,
  "RS_pct": 78.0,
  "M_up": false,
  "vol_vs_50d": 1.07,
  "pct_52w_high": 63.2,
  "above_ma50_pct": -15.8,
  "days_from_trough": 11,
  "prior60_run_pct": 14.2,
  "I_fgn60": 178002,
  "I_org60": -2375914,
  "C_qkey": "202412",
  "C_eps_yoy": 141.0,
  "C_src": "DART"
 },
 {
  "code": "103590",
  "name": "일진전기",
  "mkt": "KOSPI",
  "buy_date": "2025-05-15",
  "buy_close": 27650.0,
  "days_to_gain": 23,
  "reach_date": "2025-06-19",
  "run_max_pct": 49.0,
  "RS_pct": 83.6,
  "M_up": false,
  "vol_vs_50d": 1.8,
  "pct_52w_high": 76.3,
  "above_ma50_pct": 6.7,
  "days_from_trough": 25,
  "prior60_run_pct": 37.9,
  "I_fgn60": 49538,
  "I_org60": -1623765,
  "C_qkey": "202412",
  "C_eps_yoy": 141.0,
  "C_src": "DART"
 },
 {
  "code": "103590",
  "name": "일진전기",
  "mkt": "KOSPI",
  "buy_date": "2025-07-04",
  "buy_close": 36200.0,
  "days_to_gain": 17,
  "reach_date": "2025-07-29",
  "run_max_pct": 21.0,
  "RS_pct": 88.1,
  "M_up": true,
  "vol_vs_50d": 0.66,
  "pct_52w_high": 87.9,
  "above_ma50_pct": 18.6,
  "days_from_trough": 59,
  "prior60_run_pct": 80.5,
  "I_fgn60": 892214,
  "I_org60": 130765,
  "C_qkey": "202503",
  "C_eps_yoy": 70.8,
  "C_src": "DART"
 },
 {
  "code": "103590",
  "name": "일진전기",
  "mkt": "KOSPI",
  "buy_date": "2025-08-21",
  "buy_close": 36600.0,
  "days_to_gain": 36,
  "reach_date": "2025-10-20",
  "run_max_pct": 79.0,
  "RS_pct": 95.7,
  "M_up": true,
  "vol_vs_50d": 0.7,
  "pct_52w_high": 83.6,
  "above_ma50_pct": -4.2,
  "days_from_trough": 92,
  "prior60_run_pct": 26.0,
  "I_fgn60": 2491371,
  "I_org60": 122227,
  "C_qkey": "202506",
  "C_eps_yoy": 57.9,
  "C_src": "DART"
 },
 {
  "code": "103590",
  "name": "일진전기",
  "mkt": "KOSPI",
  "buy_date": "2025-12-01",
  "buy_close": 51800.0,
  "days_to_gain": 22,
  "reach_date": "2026-01-05",
  "run_max_pct": 29.3,
  "RS_pct": 92.9,
  "M_up": true,
  "vol_vs_50d": 0.6,
  "pct_52w_high": 79.1,
  "above_ma50_pct": 6.6,
  "days_from_trough": 158,
  "prior60_run_pct": 52.8,
  "I_fgn60": 1947650,
  "I_org60": -1279369,
  "C_qkey": "202509",
  "C_eps_yoy": 257.4,
  "C_src": "DART"
 },
 {
  "code": "103590",
  "name": "일진전기",
  "mkt": "KOSPI",
  "buy_date": "2026-02-02",
  "buy_close": 59400.0,
  "days_to_gain": 5,
  "reach_date": "2026-02-09",
  "run_max_pct": 50.7,
  "RS_pct": 88.7,
  "M_up": true,
  "vol_vs_50d": 1.39,
  "pct_52w_high": 88.7,
  "above_ma50_pct": 2.3,
  "days_from_trough": 200,
  "prior60_run_pct": 14.7,
  "I_fgn60": 66101,
  "I_org60": 77060,
  "C_qkey": "202509",
  "C_eps_yoy": 257.4,
  "C_src": "DART"
 },
 {
  "code": "103590",
  "name": "일진전기",
  "mkt": "KOSPI",
  "buy_date": "2026-03-04",
  "buy_close": 72400.0,
  "days_to_gain": 35,
  "reach_date": "2026-04-22",
  "run_max_pct": 99.0,
  "RS_pct": 89.1,
  "M_up": true,
  "vol_vs_50d": 1.32,
  "pct_52w_high": 80.9,
  "above_ma50_pct": 11.0,
  "days_from_trough": 218,
  "prior60_run_pct": 39.8,
  "I_fgn60": -125282,
  "I_org60": 86959,
  "C_qkey": "202509",
  "C_eps_yoy": 257.4,
  "C_src": "DART"
 },
 {
  "code": "445680",
  "name": "큐리옥스바이오시스템즈",
  "mkt": "KOSDAQ",
  "buy_date": "2025-03-04",
  "buy_close": 13440.0,
  "days_to_gain": 9,
  "reach_date": "2025-03-17",
  "run_max_pct": 46.9,
  "RS_pct": 31.4,
  "M_up": false,
  "vol_vs_50d": 0.79,
  "pct_52w_high": 41.4,
  "above_ma50_pct": -27.4,
  "days_from_trough": 0,
  "prior60_run_pct": 0.0,
  "I_fgn60": -66763,
  "I_org60": -137559,
  "C_qkey": "202409",
  "C_eps_yoy": -45.3,
  "C_src": "DART"
 },
 {
  "code": "445680",
  "name": "큐리옥스바이오시스템즈",
  "mkt": "KOSDAQ",
  "buy_date": "2025-03-31",
  "buy_close": 15430.0,
  "days_to_gain": 6,
  "reach_date": "2025-04-08",
  "run_max_pct": 64.3,
  "RS_pct": 45.8,
  "M_up": false,
  "vol_vs_50d": 0.31,
  "pct_52w_high": 47.6,
  "above_ma50_pct": -9.3,
  "days_from_trough": 19,
  "prior60_run_pct": 14.8,
  "I_fgn60": -7693,
  "I_org60": -9109,
  "C_qkey": "202409",
  "C_eps_yoy": -45.3,
  "C_src": "DART"
 },
 {
  "code": "445680",
  "name": "큐리옥스바이오시스템즈",
  "mkt": "KOSDAQ",
  "buy_date": "2025-04-28",
  "buy_close": 23350.0,
  "days_to_gain": 12,
  "reach_date": "2025-05-19",
  "run_max_pct": 74.7,
  "RS_pct": 66.7,
  "M_up": false,
  "vol_vs_50d": 0.81,
  "pct_52w_high": 72.0,
  "above_ma50_pct": 31.8,
  "days_from_trough": 39,
  "prior60_run_pct": 73.7,
  "I_fgn60": -147476,
  "I_org60": -134867,
  "C_qkey": "202412",
  "C_eps_yoy": 112.0,
  "C_src": "DART"
 },
 {
  "code": "445680",
  "name": "큐리옥스바이오시스템즈",
  "mkt": "KOSDAQ",
  "buy_date": "2025-05-30",
  "buy_close": 29450.0,
  "days_to_gain": 8,
  "reach_date": "2025-06-13",
  "run_max_pct": 51.1,
  "RS_pct": 80.0,
  "M_up": false,
  "vol_vs_50d": 0.64,
  "pct_52w_high": 92.8,
  "above_ma50_pct": 27.8,
  "days_from_trough": 60,
  "prior60_run_pct": 119.1,
  "I_fgn60": -188904,
  "I_org60": -328992,
  "C_qkey": "202503",
  "C_eps_yoy": -34.9,
  "C_src": "DART"
 },
 {
  "code": "445680",
  "name": "큐리옥스바이오시스템즈",
  "mkt": "KOSDAQ",
  "buy_date": "2025-06-23",
  "buy_close": 34100.0,
  "days_to_gain": 6,
  "reach_date": "2025-07-01",
  "run_max_pct": 30.5,
  "RS_pct": 86.7,
  "M_up": true,
  "vol_vs_50d": 0.67,
  "pct_52w_high": 83.6,
  "above_ma50_pct": 22.3,
  "days_from_trough": 74,
  "prior60_run_pct": 121.0,
  "I_fgn60": 68805,
  "I_org60": -804831,
  "C_qkey": "202503",
  "C_eps_yoy": -34.9,
  "C_src": "DART"
 },
 {
  "code": "445680",
  "name": "큐리옥스바이오시스템즈",
  "mkt": "KOSDAQ",
  "buy_date": "2025-07-14",
  "buy_close": 38750.0,
  "days_to_gain": 19,
  "reach_date": "2025-08-08",
  "run_max_pct": 40.1,
  "RS_pct": 89.6,
  "M_up": true,
  "vol_vs_50d": 1.84,
  "pct_52w_high": 87.1,
  "above_ma50_pct": 16.3,
  "days_from_trough": 89,
  "prior60_run_pct": 76.1,
  "I_fgn60": 80602,
  "I_org60": -868469,
  "C_qkey": "202503",
  "C_eps_yoy": -34.9,
  "C_src": "DART"
 },
 {
  "code": "445680",
  "name": "큐리옥스바이오시스템즈",
  "mkt": "KOSDAQ",
  "buy_date": "2025-08-20",
  "buy_close": 37000.0,
  "days_to_gain": 12,
  "reach_date": "2025-09-05",
  "run_max_pct": 93.8,
  "RS_pct": 93.2,
  "M_up": false,
  "vol_vs_50d": 1.41,
  "pct_52w_high": 68.1,
  "above_ma50_pct": -8.4,
  "days_from_trough": 115,
  "prior60_run_pct": 25.6,
  "I_fgn60": 284991,
  "I_org60": -758553,
  "C_qkey": "202506",
  "C_eps_yoy": -489.1,
  "C_src": "DART"
 },
 {
  "code": "445680",
  "name": "큐리옥스바이오시스템즈",
  "mkt": "KOSDAQ",
  "buy_date": "2025-10-17",
  "buy_close": 67300.0,
  "days_to_gain": 27,
  "reach_date": "2025-11-25",
  "run_max_pct": 54.5,
  "RS_pct": 98.4,
  "M_up": true,
  "vol_vs_50d": 0.75,
  "pct_52w_high": 80.8,
  "above_ma50_pct": 28.9,
  "days_from_trough": 152,
  "prior60_run_pct": 85.4,
  "I_fgn60": -772932,
  "I_org60": -191173,
  "C_qkey": "202506",
  "C_eps_yoy": -489.1,
  "C_src": "DART"
 },
 {
  "code": "445680",
  "name": "큐리옥스바이오시스템즈",
  "mkt": "KOSDAQ",
  "buy_date": "2025-12-03",
  "buy_close": 89500.0,
  "days_to_gain": 17,
  "reach_date": "2025-12-29",
  "run_max_pct": 39.1,
  "RS_pct": 98.9,
  "M_up": true,
  "vol_vs_50d": 1.22,
  "pct_52w_high": 91.5,
  "above_ma50_pct": 21.7,
  "days_from_trough": 185,
  "prior60_run_pct": 105.3,
  "I_fgn60": -1346922,
  "I_org60": 27290,
  "C_qkey": "202509",
  "C_eps_yoy": 27.2,
  "C_src": "DART"
 },
 {
  "code": "445680",
  "name": "큐리옥스바이오시스템즈",
  "mkt": "KOSDAQ",
  "buy_date": "2026-01-14",
  "buy_close": 96700.0,
  "days_to_gain": 4,
  "reach_date": "2026-01-20",
  "run_max_pct": 32.2,
  "RS_pct": 99.1,
  "M_up": true,
  "vol_vs_50d": 0.48,
  "pct_52w_high": 80.9,
  "above_ma50_pct": 5.3,
  "days_from_trough": 212,
  "prior60_run_pct": 46.7,
  "I_fgn60": -613436,
  "I_org60": 22178,
  "C_qkey": "202509",
  "C_eps_yoy": 27.2,
  "C_src": "DART"
 },
 {
  "code": "445680",
  "name": "큐리옥스바이오시스템즈",
  "mkt": "KOSDAQ",
  "buy_date": "2026-03-04",
  "buy_close": 89800.0,
  "days_to_gain": 2,
  "reach_date": "2026-03-06",
  "run_max_pct": 55.5,
  "RS_pct": 98.8,
  "M_up": false,
  "vol_vs_50d": 1.65,
  "pct_52w_high": 70.3,
  "above_ma50_pct": -19.9,
  "days_from_trough": 243,
  "prior60_run_pct": 0.3,
  "I_fgn60": 178168,
  "I_org60": -31523,
  "C_qkey": "202509",
  "C_eps_yoy": 27.2,
  "C_src": "DART"
 },
 {
  "code": "445680",
  "name": "큐리옥스바이오시스템즈",
  "mkt": "KOSDAQ",
  "buy_date": "2026-03-16",
  "buy_close": 90300.0,
  "days_to_gain": 1,
  "reach_date": "2026-03-17",
  "run_max_pct": 54.6,
  "RS_pct": 99.1,
  "M_up": true,
  "vol_vs_50d": 0.81,
  "pct_52w_high": 70.7,
  "above_ma50_pct": -19.2,
  "days_from_trough": 251,
  "prior60_run_pct": 0.6,
  "I_fgn60": 206179,
  "I_org60": -48703,
  "C_qkey": "202509",
  "C_eps_yoy": 27.2,
  "C_src": "DART"
 },
 {
  "code": "445680",
  "name": "큐리옥스바이오시스템즈",
  "mkt": "KOSDAQ",
  "buy_date": "2026-04-10",
  "buy_close": 74300.0,
  "days_to_gain": 2,
  "reach_date": "2026-04-14",
  "run_max_pct": 37.4,
  "RS_pct": 97.8,
  "M_up": false,
  "vol_vs_50d": 0.7,
  "pct_52w_high": 53.2,
  "above_ma50_pct": -30.7,
  "days_from_trough": 270,
  "prior60_run_pct": 0.0,
  "I_fgn60": 382743,
  "I_org60": 859796,
  "C_qkey": "202512",
  "C_eps_yoy": -214.4,
  "C_src": "DART"
 },
 {
  "code": "001440",
  "name": "대한전선",
  "mkt": "KOSPI",
  "buy_date": "2024-12-09",
  "buy_close": 10000.0,
  "days_to_gain": 5,
  "reach_date": "2024-12-16",
  "run_max_pct": 33.5,
  "RS_pct": 66.7,
  "M_up": false,
  "vol_vs_50d": 0.81,
  "pct_52w_high": 50.8,
  "above_ma50_pct": -15.4,
  "days_from_trough": 0,
  "prior60_run_pct": 0.0,
  "I_fgn60": -2072294,
  "I_org60": 1374955,
  "C_qkey": "202409",
  "C_eps_yoy": 35.4,
  "C_src": "DART"
 },
 {
  "code": "001440",
  "name": "대한전선",
  "mkt": "KOSPI",
  "buy_date": "2024-12-30",
  "buy_close": 11150.0,
  "days_to_gain": 11,
  "reach_date": "2025-01-16",
  "run_max_pct": 27.8,
  "RS_pct": 87.5,
  "M_up": false,
  "vol_vs_50d": 0.41,
  "pct_52w_high": 56.7,
  "above_ma50_pct": -3.6,
  "days_from_trough": 14,
  "prior60_run_pct": 11.5,
  "I_fgn60": -463428,
  "I_org60": 175241,
  "C_qkey": "202409",
  "C_eps_yoy": 35.4,
  "C_src": "DART"
 },
 {
  "code": "001440",
  "name": "대한전선",
  "mkt": "KOSPI",
  "buy_date": "2025-04-09",
  "buy_close": 10100.0,
  "days_to_gain": 22,
  "reach_date": "2025-05-14",
  "run_max_pct": 61.7,
  "RS_pct": 78.5,
  "M_up": false,
  "vol_vs_50d": 0.52,
  "pct_52w_high": 51.3,
  "above_ma50_pct": -18.6,
  "days_from_trough": 79,
  "prior60_run_pct": 0.0,
  "I_fgn60": -4870417,
  "I_org60": 2717027,
  "C_qkey": "202412",
  "C_eps_yoy": -101.7,
  "C_src": "DART"
 },
 {
  "code": "001440",
  "name": "대한전선",
  "mkt": "KOSPI",
  "buy_date": "2025-05-22",
  "buy_close": 12100.0,
  "days_to_gain": 10,
  "reach_date": "2025-06-09",
  "run_max_pct": 45.2,
  "RS_pct": 50.4,
  "M_up": false,
  "vol_vs_50d": 0.67,
  "pct_52w_high": 61.5,
  "above_ma50_pct": 2.4,
  "days_from_trough": 107,
  "prior60_run_pct": 19.8,
  "I_fgn60": -459314,
  "I_org60": 585196,
  "C_qkey": "202503",
  "C_eps_yoy": -2.6,
  "C_src": "DART"
 },
 {
  "code": "001440",
  "name": "대한전선",
  "mkt": "KOSPI",
  "buy_date": "2025-08-01",
  "buy_close": 15110.0,
  "days_to_gain": 44,
  "reach_date": "2025-10-13",
  "run_max_pct": 79.4,
  "RS_pct": 69.3,
  "M_up": true,
  "vol_vs_50d": 0.75,
  "pct_52w_high": 86.0,
  "above_ma50_pct": -2.1,
  "days_from_trough": 156,
  "prior60_run_pct": 28.7,
  "I_fgn60": -270993,
  "I_org60": -816615,
  "C_qkey": "202503",
  "C_eps_yoy": -2.6,
  "C_src": "DART"
 },
 {
  "code": "001440",
  "name": "대한전선",
  "mkt": "KOSPI",
  "buy_date": "2025-12-01",
  "buy_close": 21550.0,
  "days_to_gain": 23,
  "reach_date": "2026-01-06",
  "run_max_pct": 36.4,
  "RS_pct": 92.4,
  "M_up": true,
  "vol_vs_50d": 0.5,
  "pct_52w_high": 79.5,
  "above_ma50_pct": 6.6,
  "days_from_trough": 235,
  "prior60_run_pct": 45.2,
  "I_fgn60": 5756515,
  "I_org60": 2512230,
  "C_qkey": "202509",
  "C_eps_yoy": 63.8,
  "C_src": "DART"
 },
 {
  "code": "001440",
  "name": "대한전선",
  "mkt": "KOSPI",
  "buy_date": "2026-01-14",
  "buy_close": 25750.0,
  "days_to_gain": 15,
  "reach_date": "2026-02-04",
  "run_max_pct": 39.8,
  "RS_pct": 92.1,
  "M_up": true,
  "vol_vs_50d": 0.62,
  "pct_52w_high": 95.0,
  "above_ma50_pct": 7.5,
  "days_from_trough": 264,
  "prior60_run_pct": 46.6,
  "I_fgn60": -2749789,
  "I_org60": 4708779,
  "C_qkey": "202509",
  "C_eps_yoy": 63.8,
  "C_src": "DART"
 },
 {
  "code": "001440",
  "name": "대한전선",
  "mkt": "KOSPI",
  "buy_date": "2026-03-04",
  "buy_close": 26050.0,
  "days_to_gain": 25,
  "reach_date": "2026-04-08",
  "run_max_pct": 165.6,
  "RS_pct": 84.7,
  "M_up": true,
  "vol_vs_50d": 1.88,
  "pct_52w_high": 72.4,
  "above_ma50_pct": -6.6,
  "days_from_trough": 295,
  "prior60_run_pct": 20.9,
  "I_fgn60": 1570861,
  "I_org60": 3335415,
  "C_qkey": "202509",
  "C_eps_yoy": 63.8,
  "C_src": "DART"
 },
 {
  "code": "084370",
  "name": "유진테크",
  "mkt": "KOSDAQ",
  "buy_date": "2024-12-20",
  "buy_close": 30400.0,
  "days_to_gain": 10,
  "reach_date": "2025-01-08",
  "run_max_pct": 32.1,
  "RS_pct": 40.5,
  "M_up": false,
  "vol_vs_50d": 1.18,
  "pct_52w_high": 52.8,
  "above_ma50_pct": -13.5,
  "days_from_trough": 0,
  "prior60_run_pct": 0.0,
  "I_fgn60": -349022,
  "I_org60": -34746,
  "C_qkey": "202409",
  "C_eps_yoy": 516.4,
  "C_src": "DART"
 },
 {
  "code": "084370",
  "name": "유진테크",
  "mkt": "KOSDAQ",
  "buy_date": "2025-01-15",
  "buy_close": 35800.0,
  "days_to_gain": 20,
  "reach_date": "2025-02-18",
  "run_max_pct": 27.5,
  "RS_pct": 62.3,
  "M_up": false,
  "vol_vs_50d": 0.79,
  "pct_52w_high": 62.2,
  "above_ma50_pct": 3.6,
  "days_from_trough": 15,
  "prior60_run_pct": 17.8,
  "I_fgn60": -119603,
  "I_org60": 200912,
  "C_qkey": "202409",
  "C_eps_yoy": 516.4,
  "C_src": "DART"
 },
 {
  "code": "084370",
  "name": "유진테크",
  "mkt": "KOSDAQ",
  "buy_date": "2025-04-09",
  "buy_close": 32200.0,
  "days_to_gain": 49,
  "reach_date": "2025-06-24",
  "run_max_pct": 43.6,
  "RS_pct": 61.0,
  "M_up": false,
  "vol_vs_50d": 0.45,
  "pct_52w_high": 55.9,
  "above_ma50_pct": -20.1,
  "days_from_trough": 70,
  "prior60_run_pct": 0.0,
  "I_fgn60": -263990,
  "I_org60": 26737,
  "C_qkey": "202412",
  "C_eps_yoy": 677.0,
  "C_src": "DART"
 },
 {
  "code": "084370",
  "name": "유진테크",
  "mkt": "KOSDAQ",
  "buy_date": "2025-07-02",
  "buy_close": 37800.0,
  "days_to_gain": 10,
  "reach_date": "2025-07-16",
  "run_max_pct": 27.0,
  "RS_pct": 30.8,
  "M_up": true,
  "vol_vs_50d": 1.0,
  "pct_52w_high": 69.1,
  "above_ma50_pct": 8.2,
  "days_from_trough": 125,
  "prior60_run_pct": 21.3,
  "I_fgn60": 489390,
  "I_org60": -831885,
  "C_qkey": "202503",
  "C_eps_yoy": 27.4,
  "C_src": "DART"
 },
 {
  "code": "084370",
  "name": "유진테크",
  "mkt": "KOSDAQ",
  "buy_date": "2025-08-06",
  "buy_close": 41650.0,
  "days_to_gain": 6,
  "reach_date": "2025-08-14",
  "run_max_pct": 22.7,
  "RS_pct": 53.2,
  "M_up": true,
  "vol_vs_50d": 1.16,
  "pct_52w_high": 80.7,
  "above_ma50_pct": 4.9,
  "days_from_trough": 150,
  "prior60_run_pct": 33.7,
  "I_fgn60": 383189,
  "I_org60": -143193,
  "C_qkey": "202503",
  "C_eps_yoy": 27.4,
  "C_src": "DART"
 },
 {
  "code": "084370",
  "name": "유진테크",
  "mkt": "KOSDAQ",
  "buy_date": "2025-09-02",
  "buy_close": 45450.0,
  "days_to_gain": 8,
  "reach_date": "2025-09-12",
  "run_max_pct": 75.1,
  "RS_pct": 38.2,
  "M_up": false,
  "vol_vs_50d": 0.82,
  "pct_52w_high": 88.1,
  "above_ma50_pct": 2.7,
  "days_from_trough": 168,
  "prior60_run_pct": 32.5,
  "I_fgn60": 519230,
  "I_org60": 444448,
  "C_qkey": "202506",
  "C_eps_yoy": -11.4,
  "C_src": "DART"
 },
 {
  "code": "084370",
  "name": "유진테크",
  "mkt": "KOSDAQ",
  "buy_date": "2025-11-24",
  "buy_close": 77100.0,
  "days_to_gain": 44,
  "reach_date": "2026-01-28",
  "run_max_pct": 78.6,
  "RS_pct": 94.1,
  "M_up": false,
  "vol_vs_50d": 0.67,
  "pct_52w_high": 72.9,
  "above_ma50_pct": -4.3,
  "days_from_trough": 222,
  "prior60_run_pct": 69.6,
  "I_fgn60": -543417,
  "I_org60": 1151634,
  "C_qkey": "202509",
  "C_eps_yoy": -21.3,
  "C_src": "DART"
 },
 {
  "code": "084370",
  "name": "유진테크",
  "mkt": "KOSDAQ",
  "buy_date": "2026-02-05",
  "buy_close": 96500.0,
  "days_to_gain": 7,
  "reach_date": "2026-02-19",
  "run_max_pct": 53.4,
  "RS_pct": 92.8,
  "M_up": true,
  "vol_vs_50d": 1.21,
  "pct_52w_high": 86.9,
  "above_ma50_pct": 16.5,
  "days_from_trough": 272,
  "prior60_run_pct": 34.4,
  "I_fgn60": 305362,
  "I_org60": -26381,
  "C_qkey": "202509",
  "C_eps_yoy": -21.3,
  "C_src": "DART"
 },
 {
  "code": "084370",
  "name": "유진테크",
  "mkt": "KOSDAQ",
  "buy_date": "2026-03-04",
  "buy_close": 117900.0,
  "days_to_gain": 1,
  "reach_date": "2026-03-05",
  "run_max_pct": 25.5,
  "RS_pct": 92.5,
  "M_up": false,
  "vol_vs_50d": 1.46,
  "pct_52w_high": 85.6,
  "above_ma50_pct": 23.9,
  "days_from_trough": 287,
  "prior60_run_pct": 64.2,
  "I_fgn60": 1108745,
  "I_org60": -150844,
  "C_qkey": "202509",
  "C_eps_yoy": -21.3,
  "C_src": "DART"
 },
 {
  "code": "084370",
  "name": "유진테크",
  "mkt": "KOSDAQ",
  "buy_date": "2026-03-17",
  "buy_close": 121400.0,
  "days_to_gain": 35,
  "reach_date": "2026-05-07",
  "run_max_pct": 23.8,
  "RS_pct": 94.9,
  "M_up": true,
  "vol_vs_50d": 0.44,
  "pct_52w_high": 82.0,
  "above_ma50_pct": 15.4,
  "days_from_trough": 296,
  "prior60_run_pct": 69.1,
  "I_fgn60": 831066,
  "I_org60": -284833,
  "C_qkey": "202509",
  "C_eps_yoy": -21.3,
  "C_src": "DART"
 },
 {
  "code": "466100",
  "name": "클로봇",
  "mkt": "KOSDAQ",
  "buy_date": "2025-11-25",
  "buy_close": 34900.0,
  "days_to_gain": 5,
  "reach_date": "2025-12-02",
  "run_max_pct": 98.0,
  "RS_pct": 99.0,
  "M_up": false,
  "vol_vs_50d": 0.16,
  "pct_52w_high": 74.9,
  "above_ma50_pct": -2.1,
  "days_from_trough": 231,
  "prior60_run_pct": 91.5,
  "I_fgn60": 120568,
  "I_org60": -50218,
  "C_qkey": "202509",
  "C_eps_yoy": 140.4,
  "C_src": "DART"
 },
 {
  "code": "466100",
  "name": "클로봇",
  "mkt": "KOSDAQ",
  "buy_date": "2026-01-08",
  "buy_close": 57000.0,
  "days_to_gain": 7,
  "reach_date": "2026-01-19",
  "run_max_pct": 32.8,
  "RS_pct": 99.6,
  "M_up": true,
  "vol_vs_50d": 0.17,
  "pct_52w_high": 82.5,
  "above_ma50_pct": 17.5,
  "days_from_trough": 260,
  "prior60_run_pct": 63.3,
  "I_fgn60": -1021804,
  "I_org60": 728461,
  "C_qkey": "202509",
  "C_eps_yoy": 140.4,
  "C_src": "DART"
 },
 {
  "code": "466100",
  "name": "클로봇",
  "mkt": "KOSDAQ",
  "buy_date": "2026-03-04",
  "buy_close": 50800.0,
  "days_to_gain": 2,
  "reach_date": "2026-03-06",
  "run_max_pct": 21.3,
  "RS_pct": 93.4,
  "M_up": false,
  "vol_vs_50d": 0.47,
  "pct_52w_high": 67.1,
  "above_ma50_pct": -23.6,
  "days_from_trough": 295,
  "prior60_run_pct": 23.3,
  "I_fgn60": 841572,
  "I_org60": 2283412,
  "C_qkey": "202509",
  "C_eps_yoy": 140.4,
  "C_src": "DART"
 },
 {
  "code": "466100",
  "name": "클로봇",
  "mkt": "KOSDAQ",
  "buy_date": "2026-04-07",
  "buy_close": 40850.0,
  "days_to_gain": 8,
  "reach_date": "2026-04-17",
  "run_max_pct": 33.2,
  "RS_pct": 89.2,
  "M_up": false,
  "vol_vs_50d": 0.85,
  "pct_52w_high": 54.0,
  "above_ma50_pct": -33.6,
  "days_from_trough": 319,
  "prior60_run_pct": 0.0,
  "I_fgn60": 797099,
  "I_org60": 1100470,
  "C_qkey": "202512",
  "C_eps_yoy": -33.8,
  "C_src": "DART"
 },
 {
  "code": "127120",
  "name": "제이에스링크",
  "mkt": "KOSDAQ",
  "buy_date": "2024-12-09",
  "buy_close": 4000.0,
  "days_to_gain": 9,
  "reach_date": "2024-12-20",
  "run_max_pct": 60.2,
  "RS_pct": 79.9,
  "M_up": false,
  "vol_vs_50d": 1.98,
  "pct_52w_high": 92.0,
  "above_ma50_pct": 9.7,
  "days_from_trough": 0,
  "prior60_run_pct": 36.5,
  "I_fgn60": 219873,
  "I_org60": 0,
  "C_qkey": "202409",
  "C_eps_yoy": -212.2,
  "C_src": "DART"
 },
 {
  "code": "127120",
  "name": "제이에스링크",
  "mkt": "KOSDAQ",
  "buy_date": "2025-01-17",
  "buy_close": 5120.0,
  "days_to_gain": 16,
  "reach_date": "2025-02-14",
  "run_max_pct": 24.6,
  "RS_pct": 95.6,
  "M_up": false,
  "vol_vs_50d": 1.13,
  "pct_52w_high": 79.9,
  "above_ma50_pct": 12.1,
  "days_from_trough": 26,
  "prior60_run_pct": 50.4,
  "I_fgn60": 82367,
  "I_org60": 184,
  "C_qkey": "202409",
  "C_eps_yoy": -212.2,
  "C_src": "DART"
 },
 {
  "code": "127120",
  "name": "제이에스링크",
  "mkt": "KOSDAQ",
  "buy_date": "2025-02-21",
  "buy_close": 5840.0,
  "days_to_gain": 20,
  "reach_date": "2025-03-24",
  "run_max_pct": 68.7,
  "RS_pct": 95.6,
  "M_up": false,
  "vol_vs_50d": 0.27,
  "pct_52w_high": 91.1,
  "above_ma50_pct": 9.7,
  "days_from_trough": 47,
  "prior60_run_pct": 71.3,
  "I_fgn60": -16136,
  "I_org60": 0,
  "C_qkey": "202409",
  "C_eps_yoy": -212.2,
  "C_src": "DART"
 },
 {
  "code": "127120",
  "name": "제이에스링크",
  "mkt": "KOSDAQ",
  "buy_date": "2025-04-22",
  "buy_close": 8680.0,
  "days_to_gain": 7,
  "reach_date": "2025-05-02",
  "run_max_pct": 21.0,
  "RS_pct": 99.1,
  "M_up": false,
  "vol_vs_50d": 1.2,
  "pct_52w_high": 88.1,
  "above_ma50_pct": 24.4,
  "days_from_trough": 88,
  "prior60_run_pct": 65.6,
  "I_fgn60": -125964,
  "I_org60": 58397,
  "C_qkey": "202412",
  "C_eps_yoy": 49.2,
  "C_src": "DART"
 },
 {
  "code": "127120",
  "name": "제이에스링크",
  "mkt": "KOSDAQ",
  "buy_date": "2025-05-15",
  "buy_close": 8340.0,
  "days_to_gain": 26,
  "reach_date": "2025-06-24",
  "run_max_pct": 68.6,
  "RS_pct": 99.3,
  "M_up": false,
  "vol_vs_50d": 1.52,
  "pct_52w_high": 79.4,
  "above_ma50_pct": 4.6,
  "days_from_trough": 102,
  "prior60_run_pct": 42.8,
  "I_fgn60": -168628,
  "I_org60": -22,
  "C_qkey": "202412",
  "C_eps_yoy": 49.2,
  "C_src": "DART"
 },
 {
  "code": "127120",
  "name": "제이에스링크",
  "mkt": "KOSDAQ",
  "buy_date": "2025-07-18",
  "buy_close": 12890.0,
  "days_to_gain": 13,
  "reach_date": "2025-08-06",
  "run_max_pct": 42.6,
  "RS_pct": 99.7,
  "M_up": true,
  "vol_vs_50d": 0.7,
  "pct_52w_high": 91.7,
  "above_ma50_pct": 27.1,
  "days_from_trough": 146,
  "prior60_run_pct": 54.6,
  "I_fgn60": 11563,
  "I_org60": -50808,
  "C_qkey": "202503",
  "C_eps_yoy": -2714.3,
  "C_src": "DART"
 },
 {
  "code": "127120",
  "name": "제이에스링크",
  "mkt": "KOSDAQ",
  "buy_date": "2025-09-09",
  "buy_close": 16910.0,
  "days_to_gain": 8,
  "reach_date": "2025-09-19",
  "run_max_pct": 48.4,
  "RS_pct": 99.4,
  "M_up": true,
  "vol_vs_50d": 0.97,
  "pct_52w_high": 92.0,
  "above_ma50_pct": 11.3,
  "days_from_trough": 182,
  "prior60_run_pct": 82.6,
  "I_fgn60": 51941,
  "I_org60": 32302,
  "C_qkey": "202506",
  "C_eps_yoy": 42.1,
  "C_src": "DART"
 },
 {
  "code": "127120",
  "name": "제이에스링크",
  "mkt": "KOSDAQ",
  "buy_date": "2025-11-14",
  "buy_close": 16680.0,
  "days_to_gain": 5,
  "reach_date": "2025-11-21",
  "run_max_pct": 20.5,
  "RS_pct": 99.2,
  "M_up": true,
  "vol_vs_50d": 0.85,
  "pct_52w_high": 66.5,
  "above_ma50_pct": -18.0,
  "days_from_trough": 225,
  "prior60_run_pct": 0.0,
  "I_fgn60": -238662,
  "I_org60": 535381,
  "C_qkey": "202506",
  "C_eps_yoy": 42.1,
  "C_src": "DART"
 },
 {
  "code": "127120",
  "name": "제이에스링크",
  "mkt": "KOSDAQ",
  "buy_date": "2025-12-15",
  "buy_close": 16050.0,
  "days_to_gain": 9,
  "reach_date": "2025-12-29",
  "run_max_pct": 49.8,
  "RS_pct": 98.3,
  "M_up": true,
  "vol_vs_50d": 1.3,
  "pct_52w_high": 63.9,
  "above_ma50_pct": -18.7,
  "days_from_trough": 246,
  "prior60_run_pct": 0.0,
  "I_fgn60": -513606,
  "I_org60": 630452,
  "C_qkey": "202509",
  "C_eps_yoy": 56.2,
  "C_src": "DART"
 },
 {
  "code": "127120",
  "name": "제이에스링크",
  "mkt": "KOSDAQ",
  "buy_date": "2026-01-06",
  "buy_close": 16740.0,
  "days_to_gain": 9,
  "reach_date": "2026-01-19",
  "run_max_pct": 91.5,
  "RS_pct": 97.9,
  "M_up": true,
  "vol_vs_50d": 0.41,
  "pct_52w_high": 66.7,
  "above_ma50_pct": -10.8,
  "days_from_trough": 259,
  "prior60_run_pct": 4.3,
  "I_fgn60": -367960,
  "I_org60": 376206,
  "C_qkey": "202509",
  "C_eps_yoy": 56.2,
  "C_src": "DART"
 },
 {
  "code": "127120",
  "name": "제이에스링크",
  "mkt": "KOSDAQ",
  "buy_date": "2026-01-30",
  "buy_close": 20850.0,
  "days_to_gain": 2,
  "reach_date": "2026-02-03",
  "run_max_pct": 90.2,
  "RS_pct": 97.3,
  "M_up": true,
  "vol_vs_50d": 0.65,
  "pct_52w_high": 83.1,
  "above_ma50_pct": 9.3,
  "days_from_trough": 277,
  "prior60_run_pct": 29.9,
  "I_fgn60": 324000,
  "I_org60": 261934,
  "C_qkey": "202509",
  "C_eps_yoy": 56.2,
  "C_src": "DART"
 },
 {
  "code": "127120",
  "name": "제이에스링크",
  "mkt": "KOSDAQ",
  "buy_date": "2026-03-04",
  "buy_close": 31950.0,
  "days_to_gain": 2,
  "reach_date": "2026-03-06",
  "run_max_pct": 31.1,
  "RS_pct": 98.5,
  "M_up": false,
  "vol_vs_50d": 1.51,
  "pct_52w_high": 81.8,
  "above_ma50_pct": 32.1,
  "days_from_trough": 296,
  "prior60_run_pct": 99.1,
  "I_fgn60": 701273,
  "I_org60": 443963,
  "C_qkey": "202509",
  "C_eps_yoy": 56.2,
  "C_src": "DART"
 },
 {
  "code": "127120",
  "name": "제이에스링크",
  "mkt": "KOSDAQ",
  "buy_date": "2026-03-23",
  "buy_close": 35250.0,
  "days_to_gain": 14,
  "reach_date": "2026-04-10",
  "run_max_pct": 38.7,
  "RS_pct": 98.7,
  "M_up": true,
  "vol_vs_50d": 1.22,
  "pct_52w_high": 84.1,
  "above_ma50_pct": 18.8,
  "days_from_trough": 309,
  "prior60_run_pct": 110.6,
  "I_fgn60": 223374,
  "I_org60": 742657,
  "C_qkey": "202509",
  "C_eps_yoy": 56.2,
  "C_src": "DART"
 },
 {
  "code": "242040",
  "name": "나무기술",
  "mkt": "KOSDAQ",
  "buy_date": "2025-04-02",
  "buy_close": 1294.0,
  "days_to_gain": 15,
  "reach_date": "2025-04-23",
  "run_max_pct": 42.3,
  "RS_pct": 16.6,
  "M_up": false,
  "vol_vs_50d": 0.24,
  "pct_52w_high": 52.6,
  "above_ma50_pct": -8.7,
  "days_from_trough": 0,
  "prior60_run_pct": 0.0,
  "I_fgn60": -416477,
  "I_org60": -1075,
  "C_qkey": "202412",
  "C_eps_yoy": null,
  "C_src": "전년동기 부재/계정변형(신규상장·미공시 가능)"
 },
 {
  "code": "242040",
  "name": "나무기술",
  "mkt": "KOSDAQ",
  "buy_date": "2025-11-07",
  "buy_close": 1349.0,
  "days_to_gain": 48,
  "reach_date": "2026-01-19",
  "run_max_pct": 191.3,
  "RS_pct": 20.4,
  "M_up": true,
  "vol_vs_50d": 0.21,
  "pct_52w_high": 73.3,
  "above_ma50_pct": -5.1,
  "days_from_trough": 146,
  "prior60_run_pct": 0.0,
  "I_fgn60": -763762,
  "I_org60": -10588,
  "C_qkey": "202506",
  "C_eps_yoy": null,
  "C_src": "전년동기 부재/계정변형(신규상장·미공시 가능)"
 },
 {
  "code": "242040",
  "name": "나무기술",
  "mkt": "KOSDAQ",
  "buy_date": "2026-03-04",
  "buy_close": 3310.0,
  "days_to_gain": 1,
  "reach_date": "2026-03-05",
  "run_max_pct": 118.7,
  "RS_pct": 89.1,
  "M_up": false,
  "vol_vs_50d": 1.51,
  "pct_52w_high": 55.6,
  "above_ma50_pct": 37.0,
  "days_from_trough": 222,
  "prior60_run_pct": 151.3,
  "I_fgn60": 1055583,
  "I_org60": -1354590,
  "C_qkey": "202509",
  "C_eps_yoy": null,
  "C_src": "전년동기 부재/계정변형(신규상장·미공시 가능)"
 },
 {
  "code": "089970",
  "name": "브이엠",
  "mkt": "KOSDAQ",
  "buy_date": "2024-12-09",
  "buy_close": 5550.0,
  "days_to_gain": 2,
  "reach_date": "2024-12-11",
  "run_max_pct": 33.9,
  "RS_pct": 3.0,
  "M_up": false,
  "vol_vs_50d": 0.8,
  "pct_52w_high": 28.6,
  "above_ma50_pct": -29.8,
  "days_from_trough": 0,
  "prior60_run_pct": 0.0,
  "I_fgn60": -11254,
  "I_org60": -410779,
  "C_qkey": "202409",
  "C_eps_yoy": 12.8,
  "C_src": "DART"
 },
 {
  "code": "089970",
  "name": "브이엠",
  "mkt": "KOSDAQ",
  "buy_date": "2024-12-24",
  "buy_close": 6770.0,
  "days_to_gain": 18,
  "reach_date": "2025-01-22",
  "run_max_pct": 43.7,
  "RS_pct": 6.0,
  "M_up": false,
  "vol_vs_50d": 0.45,
  "pct_52w_high": 34.9,
  "above_ma50_pct": -8.5,
  "days_from_trough": 11,
  "prior60_run_pct": 22.0,
  "I_fgn60": -66010,
  "I_org60": -273594,
  "C_qkey": "202409",
  "C_eps_yoy": 12.8,
  "C_src": "DART"
 },
 {
  "code": "089970",
  "name": "브이엠",
  "mkt": "KOSDAQ",
  "buy_date": "2025-02-03",
  "buy_close": 6920.0,
  "days_to_gain": 9,
  "reach_date": "2025-02-14",
  "run_max_pct": 40.6,
  "RS_pct": 9.2,
  "M_up": false,
  "vol_vs_50d": 1.3,
  "pct_52w_high": 35.7,
  "above_ma50_pct": 0.3,
  "days_from_trough": 33,
  "prior60_run_pct": 24.7,
  "I_fgn60": 74685,
  "I_org60": -434578,
  "C_qkey": "202409",
  "C_eps_yoy": 12.8,
  "C_src": "DART"
 },
 {
  "code": "089970",
  "name": "브이엠",
  "mkt": "KOSDAQ",
  "buy_date": "2025-02-25",
  "buy_close": 8930.0,
  "days_to_gain": 15,
  "reach_date": "2025-03-19",
  "run_max_pct": 35.7,
  "RS_pct": 22.6,
  "M_up": false,
  "vol_vs_50d": 0.66,
  "pct_52w_high": 46.0,
  "above_ma50_pct": 19.0,
  "days_from_trough": 49,
  "prior60_run_pct": 60.9,
  "I_fgn60": 127039,
  "I_org60": -365931,
  "C_qkey": "202409",
  "C_eps_yoy": 12.8,
  "C_src": "DART"
 },
 {
  "code": "089970",
  "name": "브이엠",
  "mkt": "KOSDAQ",
  "buy_date": "2025-04-07",
  "buy_close": 10000.0,
  "days_to_gain": 14,
  "reach_date": "2025-04-25",
  "run_max_pct": 30.5,
  "RS_pct": 31.1,
  "M_up": false,
  "vol_vs_50d": 1.29,
  "pct_52w_high": 51.5,
  "above_ma50_pct": 7.0,
  "days_from_trough": 77,
  "prior60_run_pct": 46.0,
  "I_fgn60": 187871,
  "I_org60": -93963,
  "C_qkey": "202412",
  "C_eps_yoy": 133.9,
  "C_src": "DART"
 },
 {
  "code": "089970",
  "name": "브이엠",
  "mkt": "KOSDAQ",
  "buy_date": "2025-05-08",
  "buy_close": 11000.0,
  "days_to_gain": 14,
  "reach_date": "2025-05-28",
  "run_max_pct": 22.2,
  "RS_pct": 19.5,
  "M_up": false,
  "vol_vs_50d": 1.48,
  "pct_52w_high": 56.7,
  "above_ma50_pct": 3.6,
  "days_from_trough": 97,
  "prior60_run_pct": 44.2,
  "I_fgn60": 158337,
  "I_org60": 135650,
  "C_qkey": "202412",
  "C_eps_yoy": 133.9,
  "C_src": "DART"
 },
 {
  "code": "089970",
  "name": "브이엠",
  "mkt": "KOSDAQ",
  "buy_date": "2025-07-14",
  "buy_close": 10520.0,
  "days_to_gain": 35,
  "reach_date": "2025-09-02",
  "run_max_pct": 72.1,
  "RS_pct": 13.2,
  "M_up": true,
  "vol_vs_50d": 1.0,
  "pct_52w_high": 63.0,
  "above_ma50_pct": -13.5,
  "days_from_trough": 142,
  "prior60_run_pct": 0.0,
  "I_fgn60": 407949,
  "I_org60": -190486,
  "C_qkey": "202503",
  "C_eps_yoy": 153.0,
  "C_src": "DART"
 },
 {
  "code": "089970",
  "name": "브이엠",
  "mkt": "KOSDAQ",
  "buy_date": "2025-09-26",
  "buy_close": 16870.0,
  "days_to_gain": 6,
  "reach_date": "2025-10-13",
  "run_max_pct": 50.9,
  "RS_pct": 90.2,
  "M_up": true,
  "vol_vs_50d": 0.96,
  "pct_52w_high": 93.2,
  "above_ma50_pct": 32.6,
  "days_from_trough": 195,
  "prior60_run_pct": 60.7,
  "I_fgn60": 2335656,
  "I_org60": 533228,
  "C_qkey": "202506",
  "C_eps_yoy": 193.8,
  "C_src": "DART"
 },
 {
  "code": "089970",
  "name": "브이엠",
  "mkt": "KOSDAQ",
  "buy_date": "2025-11-03",
  "buy_close": 23450.0,
  "days_to_gain": 25,
  "reach_date": "2025-12-08",
  "run_max_pct": 35.4,
  "RS_pct": 96.6,
  "M_up": true,
  "vol_vs_50d": 1.0,
  "pct_52w_high": 92.1,
  "above_ma50_pct": 35.3,
  "days_from_trough": 216,
  "prior60_run_pct": 123.3,
  "I_fgn60": 331920,
  "I_org60": 3829865,
  "C_qkey": "202506",
  "C_eps_yoy": 193.8,
  "C_src": "DART"
 },
 {
  "code": "089970",
  "name": "브이엠",
  "mkt": "KOSDAQ",
  "buy_date": "2025-12-16",
  "buy_close": 26150.0,
  "days_to_gain": 11,
  "reach_date": "2026-01-05",
  "run_max_pct": 21.4,
  "RS_pct": 98.4,
  "M_up": true,
  "vol_vs_50d": 0.38,
  "pct_52w_high": 88.5,
  "above_ma50_pct": 6.8,
  "days_from_trough": 247,
  "prior60_run_pct": 76.1,
  "I_fgn60": 212977,
  "I_org60": 4902515,
  "C_qkey": "202509",
  "C_eps_yoy": 466.2,
  "C_src": "DART"
 },
 {
  "code": "089970",
  "name": "브이엠",
  "mkt": "KOSDAQ",
  "buy_date": "2026-01-22",
  "buy_close": 24600.0,
  "days_to_gain": 5,
  "reach_date": "2026-01-29",
  "run_max_pct": 71.7,
  "RS_pct": 96.5,
  "M_up": true,
  "vol_vs_50d": 1.18,
  "pct_52w_high": 77.5,
  "above_ma50_pct": -9.2,
  "days_from_trough": 271,
  "prior60_run_pct": 5.6,
  "I_fgn60": 559141,
  "I_org60": 699097,
  "C_qkey": "202509",
  "C_eps_yoy": 466.2,
  "C_src": "DART"
 },
 {
  "code": "089970",
  "name": "브이엠",
  "mkt": "KOSDAQ",
  "buy_date": "2026-02-05",
  "buy_close": 27150.0,
  "days_to_gain": 4,
  "reach_date": "2026-02-11",
  "run_max_pct": 59.9,
  "RS_pct": 96.3,
  "M_up": true,
  "vol_vs_50d": 1.91,
  "pct_52w_high": 85.5,
  "above_ma50_pct": -2.0,
  "days_from_trough": 281,
  "prior60_run_pct": 16.5,
  "I_fgn60": 711851,
  "I_org60": 200446,
  "C_qkey": "202509",
  "C_eps_yoy": 466.2,
  "C_src": "DART"
 },
 {
  "code": "089970",
  "name": "브이엠",
  "mkt": "KOSDAQ",
  "buy_date": "2026-03-04",
  "buy_close": 32750.0,
  "days_to_gain": 1,
  "reach_date": "2026-03-05",
  "run_max_pct": 49.0,
  "RS_pct": 95.5,
  "M_up": false,
  "vol_vs_50d": 0.96,
  "pct_52w_high": 77.5,
  "above_ma50_pct": 7.5,
  "days_from_trough": 296,
  "prior60_run_pct": 37.0,
  "I_fgn60": 1270286,
  "I_org60": 361599,
  "C_qkey": "202509",
  "C_eps_yoy": 466.2,
  "C_src": "DART"
 },
 {
  "code": "089970",
  "name": "브이엠",
  "mkt": "KOSDAQ",
  "buy_date": "2026-03-13",
  "buy_close": 38700.0,
  "days_to_gain": 4,
  "reach_date": "2026-03-19",
  "run_max_pct": 29.2,
  "RS_pct": 97.4,
  "M_up": true,
  "vol_vs_50d": 0.27,
  "pct_52w_high": 89.2,
  "above_ma50_pct": 20.4,
  "days_from_trough": 303,
  "prior60_run_pct": 57.3,
  "I_fgn60": 664494,
  "I_org60": 409485,
  "C_qkey": "202509",
  "C_eps_yoy": 466.2,
  "C_src": "DART"
 },
 {
  "code": "089970",
  "name": "브이엠",
  "mkt": "KOSDAQ",
  "buy_date": "2026-03-31",
  "buy_close": 38750.0,
  "days_to_gain": 10,
  "reach_date": "2026-04-14",
  "run_max_pct": 54.8,
  "RS_pct": 97.3,
  "M_up": false,
  "vol_vs_50d": 0.74,
  "pct_52w_high": 79.4,
  "above_ma50_pct": 8.3,
  "days_from_trough": 315,
  "prior60_run_pct": 57.5,
  "I_fgn60": 913799,
  "I_org60": -39162,
  "C_qkey": "202509",
  "C_eps_yoy": 466.2,
  "C_src": "DART"
 },
 {
  "code": "044490",
  "name": "태웅",
  "mkt": "KOSDAQ",
  "buy_date": "2024-12-09",
  "buy_close": 9250.0,
  "days_to_gain": 10,
  "reach_date": "2024-12-23",
  "run_max_pct": 40.4,
  "RS_pct": 17.4,
  "M_up": false,
  "vol_vs_50d": 0.86,
  "pct_52w_high": 39.6,
  "above_ma50_pct": -28.3,
  "days_from_trough": 0,
  "prior60_run_pct": 0.0,
  "I_fgn60": -352846,
  "I_org60": -14315,
  "C_qkey": "202409",
  "C_eps_yoy": -77.4,
  "C_src": "DART"
 },
 {
  "code": "044490",
  "name": "태웅",
  "mkt": "KOSDAQ",
  "buy_date": "2025-01-09",
  "buy_close": 11400.0,
  "days_to_gain": 23,
  "reach_date": "2025-02-17",
  "run_max_pct": 44.8,
  "RS_pct": 29.8,
  "M_up": false,
  "vol_vs_50d": 0.5,
  "pct_52w_high": 48.8,
  "above_ma50_pct": -0.9,
  "days_from_trough": 20,
  "prior60_run_pct": 23.2,
  "I_fgn60": -306511,
  "I_org60": -190281,
  "C_qkey": "202409",
  "C_eps_yoy": -77.4,
  "C_src": "DART"
 },
 {
  "code": "044490",
  "name": "태웅",
  "mkt": "KOSDAQ",
  "buy_date": "2025-02-24",
  "buy_close": 13270.0,
  "days_to_gain": 14,
  "reach_date": "2025-03-17",
  "run_max_pct": 25.5,
  "RS_pct": 62.9,
  "M_up": false,
  "vol_vs_50d": 0.62,
  "pct_52w_high": 56.8,
  "above_ma50_pct": 11.9,
  "days_from_trough": 48,
  "prior60_run_pct": 43.5,
  "I_fgn60": -17991,
  "I_org60": 95827,
  "C_qkey": "202409",
  "C_eps_yoy": -77.4,
  "C_src": "DART"
 },
 {
  "code": "044490",
  "name": "태웅",
  "mkt": "KOSDAQ",
  "buy_date": "2025-03-28",
  "buy_close": 14020.0,
  "days_to_gain": 30,
  "reach_date": "2025-05-14",
  "run_max_pct": 135.0,
  "RS_pct": 51.1,
  "M_up": false,
  "vol_vs_50d": 0.99,
  "pct_52w_high": 60.0,
  "above_ma50_pct": 2.6,
  "days_from_trough": 71,
  "prior60_run_pct": 25.9,
  "I_fgn60": 346239,
  "I_org60": 9693,
  "C_qkey": "202409",
  "C_eps_yoy": -77.4,
  "C_src": "DART"
 },
 {
  "code": "044490",
  "name": "태웅",
  "mkt": "KOSDAQ",
  "buy_date": "2025-05-16",
  "buy_close": 13830.0,
  "days_to_gain": 5,
  "reach_date": "2025-05-23",
  "run_max_pct": 140.4,
  "RS_pct": 13.6,
  "M_up": false,
  "vol_vs_50d": 3.62,
  "pct_52w_high": 59.2,
  "above_ma50_pct": -8.9,
  "days_from_trough": 103,
  "prior60_run_pct": 4.2,
  "I_fgn60": 510025,
  "I_org60": -139938,
  "C_qkey": "202503",
  "C_eps_yoy": -77.5,
  "C_src": "DART"
 },
 {
  "code": "044490",
  "name": "태웅",
  "mkt": "KOSDAQ",
  "buy_date": "2025-07-01",
  "buy_close": 30000.0,
  "days_to_gain": 14,
  "reach_date": "2025-07-21",
  "run_max_pct": 45.7,
  "RS_pct": 91.9,
  "M_up": true,
  "vol_vs_50d": 0.42,
  "pct_52w_high": 81.4,
  "above_ma50_pct": 34.6,
  "days_from_trough": 133,
  "prior60_run_pct": 116.9,
  "I_fgn60": 324743,
  "I_org60": 503527,
  "C_qkey": "202503",
  "C_eps_yoy": -77.5,
  "C_src": "DART"
 },
 {
  "code": "044490",
  "name": "태웅",
  "mkt": "KOSDAQ",
  "buy_date": "2025-09-25",
  "buy_close": 30900.0,
  "days_to_gain": 10,
  "reach_date": "2025-10-16",
  "run_max_pct": 20.2,
  "RS_pct": 95.3,
  "M_up": true,
  "vol_vs_50d": 0.57,
  "pct_52w_high": 70.7,
  "above_ma50_pct": -17.2,
  "days_from_trough": 194,
  "prior60_run_pct": 3.0,
  "I_fgn60": -200282,
  "I_org60": 366671,
  "C_qkey": "202506",
  "C_eps_yoy": -69.3,
  "C_src": "DART"
 },
 {
  "code": "044490",
  "name": "태웅",
  "mkt": "KOSDAQ",
  "buy_date": "2025-11-21",
  "buy_close": 23200.0,
  "days_to_gain": 10,
  "reach_date": "2025-12-05",
  "run_max_pct": 34.5,
  "RS_pct": 88.1,
  "M_up": false,
  "vol_vs_50d": 0.37,
  "pct_52w_high": 53.1,
  "above_ma50_pct": -24.3,
  "days_from_trough": 230,
  "prior60_run_pct": 0.0,
  "I_fgn60": 135804,
  "I_org60": -979944,
  "C_qkey": "202509",
  "C_eps_yoy": -11.5,
  "C_src": "DART"
 },
 {
  "code": "044490",
  "name": "태웅",
  "mkt": "KOSDAQ",
  "buy_date": "2026-01-02",
  "buy_close": 24450.0,
  "days_to_gain": 11,
  "reach_date": "2026-01-19",
  "run_max_pct": 37.0,
  "RS_pct": 92.3,
  "M_up": true,
  "vol_vs_50d": 0.76,
  "pct_52w_high": 55.9,
  "above_ma50_pct": -8.7,
  "days_from_trough": 257,
  "prior60_run_pct": 5.4,
  "I_fgn60": -388998,
  "I_org60": -382473,
  "C_qkey": "202509",
  "C_eps_yoy": -11.5,
  "C_src": "DART"
 },
 {
  "code": "044490",
  "name": "태웅",
  "mkt": "KOSDAQ",
  "buy_date": "2026-02-06",
  "buy_close": 28400.0,
  "days_to_gain": 7,
  "reach_date": "2026-02-20",
  "run_max_pct": 101.8,
  "RS_pct": 91.6,
  "M_up": true,
  "vol_vs_50d": 0.61,
  "pct_52w_high": 65.0,
  "above_ma50_pct": 1.4,
  "days_from_trough": 282,
  "prior60_run_pct": 22.4,
  "I_fgn60": -563074,
  "I_org60": 250645,
  "C_qkey": "202509",
  "C_eps_yoy": -11.5,
  "C_src": "DART"
 },
 {
  "code": "044490",
  "name": "태웅",
  "mkt": "KOSDAQ",
  "buy_date": "2026-03-04",
  "buy_close": 27150.0,
  "days_to_gain": 1,
  "reach_date": "2026-03-05",
  "run_max_pct": 111.0,
  "RS_pct": 83.3,
  "M_up": false,
  "vol_vs_50d": 0.9,
  "pct_52w_high": 62.1,
  "above_ma50_pct": -9.4,
  "days_from_trough": 296,
  "prior60_run_pct": 16.5,
  "I_fgn60": -409570,
  "I_org60": 562141,
  "C_qkey": "202509",
  "C_eps_yoy": -11.5,
  "C_src": "DART"
 },
 {
  "code": "044490",
  "name": "태웅",
  "mkt": "KOSDAQ",
  "buy_date": "2026-03-17",
  "buy_close": 42800.0,
  "days_to_gain": 3,
  "reach_date": "2026-03-20",
  "run_max_pct": 33.9,
  "RS_pct": 95.4,
  "M_up": true,
  "vol_vs_50d": 0.76,
  "pct_52w_high": 85.6,
  "above_ma50_pct": 29.7,
  "days_from_trough": 305,
  "prior60_run_pct": 75.1,
  "I_fgn60": -32838,
  "I_org60": 921615,
  "C_qkey": "202509",
  "C_eps_yoy": -11.5,
  "C_src": "DART"
 },
 {
  "code": "044490",
  "name": "태웅",
  "mkt": "KOSDAQ",
  "buy_date": "2026-04-02",
  "buy_close": 44350.0,
  "days_to_gain": 16,
  "reach_date": "2026-04-24",
  "run_max_pct": 32.6,
  "RS_pct": 94.3,
  "M_up": false,
  "vol_vs_50d": 0.98,
  "pct_52w_high": 77.4,
  "above_ma50_pct": 16.9,
  "days_from_trough": 317,
  "prior60_run_pct": 81.4,
  "I_fgn60": 110164,
  "I_org60": 1169598,
  "C_qkey": "202512",
  "C_eps_yoy": -104.4,
  "C_src": "DART"
 },
 {
  "code": "090360",
  "name": "로보스타",
  "mkt": "KOSDAQ",
  "buy_date": "2024-12-09",
  "buy_close": 18010.0,
  "days_to_gain": 14,
  "reach_date": "2024-12-30",
  "run_max_pct": 68.5,
  "RS_pct": 27.3,
  "M_up": false,
  "vol_vs_50d": 1.41,
  "pct_52w_high": 49.5,
  "above_ma50_pct": -17.0,
  "days_from_trough": 0,
  "prior60_run_pct": 0.0,
  "I_fgn60": -91609,
  "I_org60": 12269,
  "C_qkey": "202409",
  "C_eps_yoy": -765.7,
  "C_src": "DART"
 },
 {
  "code": "090360",
  "name": "로보스타",
  "mkt": "KOSDAQ",
  "buy_date": "2025-04-09",
  "buy_close": 20200.0,
  "days_to_gain": 4,
  "reach_date": "2025-04-15",
  "run_max_pct": 32.4,
  "RS_pct": 22.7,
  "M_up": false,
  "vol_vs_50d": 0.3,
  "pct_52w_high": 57.2,
  "above_ma50_pct": -21.2,
  "days_from_trough": 79,
  "prior60_run_pct": 0.0,
  "I_fgn60": -12262,
  "I_org60": 9254,
  "C_qkey": "202412",
  "C_eps_yoy": 131.8,
  "C_src": "DART"
 },
 {
  "code": "090360",
  "name": "로보스타",
  "mkt": "KOSDAQ",
  "buy_date": "2025-05-02",
  "buy_close": 24200.0,
  "days_to_gain": 32,
  "reach_date": "2025-06-23",
  "run_max_pct": 29.3,
  "RS_pct": 41.7,
  "M_up": false,
  "vol_vs_50d": 0.4,
  "pct_52w_high": 76.6,
  "above_ma50_pct": 0.2,
  "days_from_trough": 95,
  "prior60_run_pct": 19.8,
  "I_fgn60": 36133,
  "I_org60": -14912,
  "C_qkey": "202412",
  "C_eps_yoy": 131.8,
  "C_src": "DART"
 },
 {
  "code": "090360",
  "name": "로보스타",
  "mkt": "KOSDAQ",
  "buy_date": "2025-07-14",
  "buy_close": 27250.0,
  "days_to_gain": 44,
  "reach_date": "2025-09-15",
  "run_max_pct": 157.2,
  "RS_pct": 50.7,
  "M_up": true,
  "vol_vs_50d": 0.18,
  "pct_52w_high": 87.1,
  "above_ma50_pct": 3.4,
  "days_from_trough": 142,
  "prior60_run_pct": 15.5,
  "I_fgn60": -187266,
  "I_org60": 31952,
  "C_qkey": "202503",
  "C_eps_yoy": -907.1,
  "C_src": "DART"
 },
 {
  "code": "090360",
  "name": "로보스타",
  "mkt": "KOSDAQ",
  "buy_date": "2025-10-02",
  "buy_close": 42750.0,
  "days_to_gain": 3,
  "reach_date": "2025-10-14",
  "run_max_pct": 137.9,
  "RS_pct": 92.6,
  "M_up": true,
  "vol_vs_50d": 1.29,
  "pct_52w_high": 83.5,
  "above_ma50_pct": 32.3,
  "days_from_trough": 199,
  "prior60_run_pct": 69.3,
  "I_fgn60": 162079,
  "I_org60": -2754,
  "C_qkey": "202506",
  "C_eps_yoy": -176.0,
  "C_src": "DART"
 },
 {
  "code": "090360",
  "name": "로보스타",
  "mkt": "KOSDAQ",
  "buy_date": "2025-11-25",
  "buy_close": 62600.0,
  "days_to_gain": 6,
  "reach_date": "2025-12-03",
  "run_max_pct": 33.4,
  "RS_pct": 97.4,
  "M_up": false,
  "vol_vs_50d": 0.14,
  "pct_52w_high": 61.6,
  "above_ma50_pct": -0.5,
  "days_from_trough": 232,
  "prior60_run_pct": 128.1,
  "I_fgn60": 174548,
  "I_org60": 14881,
  "C_qkey": "202509",
  "C_eps_yoy": 76.4,
  "C_src": "DART"
 },
 {
  "code": "090360",
  "name": "로보스타",
  "mkt": "KOSDAQ",
  "buy_date": "2025-12-18",
  "buy_close": 71700.0,
  "days_to_gain": 19,
  "reach_date": "2026-01-19",
  "run_max_pct": 26.8,
  "RS_pct": 97.9,
  "M_up": true,
  "vol_vs_50d": 0.17,
  "pct_52w_high": 70.5,
  "above_ma50_pct": -3.2,
  "days_from_trough": 249,
  "prior60_run_pct": 67.7,
  "I_fgn60": -240639,
  "I_org60": -60599,
  "C_qkey": "202509",
  "C_eps_yoy": 76.4,
  "C_src": "DART"
 },
 {
  "code": "090360",
  "name": "로보스타",
  "mkt": "KOSDAQ",
  "buy_date": "2026-03-04",
  "buy_close": 58900.0,
  "days_to_gain": 38,
  "reach_date": "2026-04-27",
  "run_max_pct": 50.8,
  "RS_pct": 85.4,
  "M_up": false,
  "vol_vs_50d": 0.55,
  "pct_52w_high": 57.9,
  "above_ma50_pct": -25.7,
  "days_from_trough": 296,
  "prior60_run_pct": 0.0,
  "I_fgn60": 85861,
  "I_org60": 278817,
  "C_qkey": "202509",
  "C_eps_yoy": 76.4,
  "C_src": "DART"
 },
 {
  "code": "090360",
  "name": "로보스타",
  "mkt": "KOSDAQ",
  "buy_date": "2026-05-07",
  "buy_close": 68400.0,
  "days_to_gain": 6,
  "reach_date": "2026-05-15",
  "run_max_pct": 29.8,
  "RS_pct": 90.1,
  "M_up": true,
  "vol_vs_50d": 0.63,
  "pct_52w_high": 67.3,
  "above_ma50_pct": 4.8,
  "days_from_trough": 340,
  "prior60_run_pct": 23.2,
  "I_fgn60": -115905,
  "I_org60": 158732,
  "C_qkey": "202512",
  "C_eps_yoy": -145.6,
  "C_src": "DART"
 }
]