{
 "086670": {
  "n": 600,
  "first": "2023-11-28",
  "last": "2026-05-19"
 },
 "086710": {
  "n": 600,
  "first": "2023-11-28",
  "last": "2026-05-19"
 },
 "086820": {
  "n": 600,
  "first": "2023-11-28",
  "last": "2026-05-19"
 },
 "086900": {
  "n": 600,
  "first": "2023-11-28",
  "last": "2026-05-19"
 },
 "086980": {
  "n": 600,
  "first": "2023-11-28",
  "last": "2026-05-19"
 },
 "087010": {
  "n": 600,
  "first": "2023-11-28",
  "last": "2026-05-19"
 },
 "087600": {
  "n": 600,
  "first": "2023-11-28",
  "last": "2026-05-19"
 },
 "088130": {
  "n": 600,
  "first": "2023-11-28",
  "last": "2026-05-19"
 },
 "088290": {
  "n": 600,
  "first": "2023-11-28",
  "last": "2026-05-19"
 },
 "088350": {
  "n": 600,
  "first": "2023-11-28",
  "last": "2026-05-19"
 },
 "088390": {
  "n": 600,
  "first": "2023-11-28",
  "last": "2026-05-19"
 },
 "089010": {
  "n": 600,
  "first": "2023-11-28",
  "last": "2026-05-19"
 },
 "089030": {
  "n": 600,
  "first": "2023-11-28",
  "last": "2026-05-19"
 },
 "089150": {
  "n": 600,
  "first": "2023-11-28",
  "last": "2026-05-19"
 },
 "089230": {
  "n": 600,
  "first": "2023-11-28",
  "last": "2026-05-19"
 },
 "089600": {
  "n": 600,
  "first": "2023-11-28",
  "last": "2026-05-19"
 },
 "089790": {
  "n": 600,
  "first": "2023-11-28",
  "last": "2026-05-19"
 },
 "089850": {
  "n": 600,
  "first": "2023-11-28",
  "last": "2026-05-19"
 },
 "089890": {
  "n": 600,
  "first": "2023-11-28",
  "last": "2026-05-19"
 },
 "089970": {
  "n": 600,
  "first": "2023-11-28",
  "last": "2026-05-19"
 },
 "090080": {
  "n": 600,
  "first": "2023-11-28",
  "last": "2026-05-19"
 },
 "090350": {
  "n": 600,
  "first": "2023-11-28",
  "last": "2026-05-19"
 },
 "090355": {
  "n": 600,
  "first": "2023-11-28",
  "last": "2026-05-19"
 },
 "090360": {
  "n": 600,
  "first": "2023-11-28",
  "last": "2026-05-19"
 },
 "090435": {
  "n": 600,
  "first": "2023-11-28",
  "last": "2026-05-19"
 },
 "090470": {
  "n": 600,
  "first": "2023-11-28",
  "last": "2026-05-19"
 },
 "090710": {
  "n": 600,
  "first": "2023-11-28",
  "last": "2026-05-19"
 },
 "091120": {
  "n": 600,
  "first": "2023-11-28",
  "last": "2026-05-19"
 },
 "091440": {
  "n": 600,
  "first": "2023-11-28",
  "last": "2026-05-19"
 },
 "091580": {
  "n": 600,
  "first": "2023-11-28",
  "last": "2026-05-19"
 },
 "091810": {
  "n": 600,
  "first": "2023-11-28",
  "last": "2026-05-19"
 },
 "092070": {
  "n": 600,
  "first": "2023-11-28",
  "last": "2026-05-19"
 },
 "092200": {
  "n": 600,
  "first": "2023-11-28",
  "last": "2026-05-19"
 },
 "092220": {
  "n": 600,
  "first": "2023-11-28",
  "last": "2026-05-19"
 },
 "092460": {
  "n": 600,
  "first": "2023-11-28",
  "last": "2026-05-19"
 },
 "092730": {
  "n": 600,
  "first": "2023-11-28",
  "last": "2026-05-19"
 },
 "092790": {
  "n": 600,
  "first": "2023-11-28",
  "last": "2026-05-19"
 },
 "092870": {
  "n": 600,
  "first": "2023-11-28",
  "last": "2026-05-19"
 },
 "093240": {
  "n": 600,
  "first": "2023-11-28",
  "last": "2026-05-19"
 },
 "093320": {
  "n": 600,
  "first": "2023-11-28",
  "last": "2026-05-19"
 },
 "093370": {
  "n": 600,
  "first": "2023-11-28",
  "last": "2026-05-19"
 },
 "093520": {
  "n": 600,
  "first": "2023-11-28",
  "last": "2026-05-19"
 },
 "093640": {
  "n": 600,
  "first": "2023-11-28",
  "last": "2026-05-19"
 },
 "094170": {
  "n": 600,
  "first": "2023-11-28",
  "last": "2026-05-19"
 },
 "094360": {
  "n": 600,
  "first": "2023-11-28",
  "last": "2026-05-19"
 },
 "094480": {
  "n": 600,
  "first": "2023-11-28",
  "last": "2026-05-19"
 },
 "094820": {
  "n": 600,
  "first": "2023-11-28",
  "last": "2026-05-19"
 },
 "094840": {
  "n": 600,
  "first": "2023-11-28",
  "last": "2026-05-19"
 },
 "094940": {
  "n": 600,
  "first": "2023-11-28",
  "last": "2026-05-19"
 },
 "095270": {
  "n": 600,
  "first": "2023-11-28",
  "last": "2026-05-19"
 },
 "095340": {
  "n": 600,
  "first": "2023-11-28",
  "last": "2026-05-19"
 },
 "095500": {
  "n": 600,
  "first": "2023-11-28",
  "last": "2026-05-19"
 },
 "095610": {
  "n": 600,
  "first": "2023-11-28",
  "last": "2026-05-19"
 },
 "095910": {
  "n": 600,
  "first": "2023-11-28",
  "last": "2026-05-19"
 },
 "096350": {
  "n": 600,
  "first": "2023-11-28",
  "last": "2026-05-19"
 },
 "096530": {
  "n": 600,
  "first": "2023-11-28",
  "last": "2026-05-19"
 },
 "096630": {
  "n": 600,
  "first": "2023-11-28",
  "last": "2026-05-19"
 },
 "097230": {
  "n": 600,
  "first": "2023-11-28",
  "last": "2026-05-19"
 },
 "097800": {
  "n": 600,
  "first": "2023-11-28",
  "last": "2026-05-19"
 },
 "097870": {
  "n": 600,
  "first": "2023-11-28",
  "last": "2026-05-19"
 },
 "098460": {
  "n": 600,
  "first": "2023-11-28",
  "last": "2026-05-19"
 },
 "098660": {
  "n": 600,
  "first": "2023-11-28",
  "last": "2026-05-19"
 },
 "099190": {
  "n": 600,
  "first": "2023-11-28",
  "last": "2026-05-19"
 },
 "099220": {
  "n": 600,
  "first": "2023-11-28",
  "last": "2026-05-19"
 },
 "099320": {
  "n": 600,
  "first": "2023-11-28",
  "last": "2026-05-19"
 }
}